Workbook

Sheet project
A1: Project ID | B1: ID Old | C1: Project Name Full | D1: Objetivo | E1: Blend Project Type | F1: Sigla | G1: Type Project | H1: Client Name | I1: Status | J1: Folder Legal | K1: Foldel Project Admin | L1: Project Manager | M1: Account Manager | N1: Technical Leader | O1: Sr Tech | P1: Contract Type | Q1: Support Engineer | R1: NetSuite | S1: Team | T1: Tipo de contrato | U1: Contrato | V1: CET | W1: Ficha tecnica | X1: Legal | Y1: Kick off | Z1: Comites de estión
A2: P0083 | B2: P0105 | C2: COE – Center of Excellence (Reuniones internas / Entrega interna de proyectos dedicado) | D2: COE - Center of Excellence | E2: Internal | F2: BLD | G2: Interno | H2: =_xlfn.IFNA(VLOOKUP(F2,clientes!A:B,2,FALSE()),"--") -> Blend360 | I2: Activo | J2: N.A. | K2: N.A. | L2: N.A. | M2: N.A. | N2: N.A. | O2: N.A. | P2: In Progress | Q2: N. A. | R2: 5045 | S2: No Aplica
A3: P0089 | B3: P0221 | C3: =F3&" - "&D3&" - "&E3 -> BLD - Meetings & Training - Internal | D3: Meetings & Training | E3: Internal | F3: BLD | G3: Interno | H3: =_xlfn.IFNA(VLOOKUP(F3,clientes!A:B,2,FALSE()),"--") -> Blend360 | I3: Activo | J3: N.A. | K3: N.A. | L3: N.A. | M3: N.A. | N3: N.A. | O3: N.A. | P3: In Progress | Q3: N. A. | R3: 5045 | S3: No Aplica
A4: P0094 | B4: P0312 | C4: =F4&" - "&D4&" - "&E4 -> BLD - Time Off & Holiday - Internal | D4: Time Off & Holiday | E4: Internal | F4: BLD | G4: Interno | H4: =_xlfn.IFNA(VLOOKUP(F4,clientes!A:B,2,FALSE()),"--") -> Blend360 | I4: Activo | J4: N.A. | K4: N.A. | L4: N.A. | M4: N.A. | N4: N.A. | O4: N.A. | P4: In Progress | Q4: N. A. | R4: 5045 | S4: No Aplica
A5: P1920 | B5: P0070 | C5: =F5&" - "&D5&" - "&E5 -> BTG - SmartCash - Operación - Ret SW | D5: SmartCash - Operación | E5: Ret SW | F5: BTG | G5: Software SW | H5: =_xlfn.IFNA(VLOOKUP(F5,clientes!A:B,2,FALSE()),"--") -> BTG Pactual Colombia | I5: Activo | J5: BTG Pactual S.A | K5: Cto Mantenimiento y soporte CP Suite | L5: Oscar Barragan | M5: Nicolas Avella | N5: Juan Zambrano | O5: Ariane Hernandez | P5: In Progress | Q5: Miguel.Carrillo | R5: 55132 - Ret SW 56836 - Ret | S5: No Aplica
A6: P2012 | B6: P0070 | C6: =F6&" - "&D6&" - "&E6 -> BTG - SmartCash - Operación - Ret | D6: SmartCash - Operación | E6: Ret | F6: BTG | G6: Operación | H6: BTG Pactual | I6: Activo | J6: BTG Pactual S.A | K6: BTG COLOMBIA 13.580 | L6: Oscar Barragan | M6: Nicolas Avella | N6: Juan Zambrano | O6: Ariane Hernandez | P6: In Progress | Q6: Miguel.Carrillo | R6: 55132 - Ret SW 56836 - Ret | S6: Operations_Team_01
A7: P1903 | B7: P0337 | C7: =F7&" - "&D7&" - "&E7 -> ACA - Catastro Cali Piloto Dashboard - Cloud | D7: Catastro Cali Piloto Dashboard | E7: Cloud | F7: ACA | G7: Data | H7: =_xlfn.IFNA(VLOOKUP(F7,clientes!A:B,2,FALSE()),"--") -> Alcaldia de Cali | I7: Inactivo | J7: Alcadia de Cali | K7: N.A. | L7: Kelly Carbonell | M7: Karen Arandia | N7: Carlos Sierra | O7: Simón Lopez | P7: Complete | Q7: N. A. | R7: 55115 - CLOUD 55116 - Fixed | S7: No Aplica
A8: P1904 | B8: P0337 | C8: =F8&" - "&D8&" - "&E8 -> ACA - Catastro Cali Piloto Dashboard - Fixed | D8: Catastro Cali Piloto Dashboard | E8: Fixed | F8: ACA | G8: Implementación | H8: =_xlfn.IFNA(VLOOKUP(F8,clientes!A:B,2,FALSE()),"--") -> Alcaldia de Cali | I8: Inactivo | J8: Alcadia de Cali | K8: N.A. | L8: Kelly Carbonell | M8: Karen Arandia | N8: Carlos Sierra | O8: Simón Lopez | P8: Complete | Q8: N. A. | R8: 55115 - CLOUD 55116 - Fixed | S8: Simón Lopez
A9: P1905 | B9: P0323 | C9: =F9&" - "&D9&" - "&E9 -> ACA - Fase 1 Datacali - Fixed | D9: Fase 1 Datacali | E9: Fixed | F9: ACA | G9: Implementación | H9: =_xlfn.IFNA(VLOOKUP(F9,clientes!A:B,2,FALSE()),"--") -> Alcaldia de Cali | I9: Inactivo | J9: Alcadia de Cali | K9: Contrato No. 4134.010.26.1.0441-2024 | L9: Kelly Carbonell | M9: Karen Arandia | N9: Carlos Sierra | O9: Simón Lopez | P9: Complete | Q9: N. A. | R9: 55117 - Fixed 55118 - Ret SW 55119 - CLOUD | S9: Simón Lopez
A10: P1906 | B10: P0323 | C10: =F10&" - "&D10&" - "&E10 -> ACA - Fase 1 Datacali - Ret SW | D10: Fase 1 Datacali | E10: Ret SW | F10: ACA | G10: Software SW | H10: =_xlfn.IFNA(VLOOKUP(F10,clientes!A:B,2,FALSE()),"--") -> Alcaldia de Cali | I10: Inactivo | J10: Alcadia de Cali | K10: Contrato No. 4134.010.26.1.0441-2024 | L10: Kelly Carbonell | M10: Karen Arandia | N10: Carlos Sierra | O10: Simón Lopez | P10: Complete | Q10: N. A. | R10: 55117 - Fixed 55118 - Ret SW 55119 - CLOUD | S10: No Aplica
A11: P1907 | B11: P0323 | C11: =F11&" - "&D11&" - "&E11 -> ACA - Fase 1 Datacali - Cloud | D11: Fase 1 Datacali | E11: Cloud | F11: ACA | G11: Data | H11: =_xlfn.IFNA(VLOOKUP(F11,clientes!A:B,2,FALSE()),"--") -> Alcaldia de Cali | I11: Inactivo | J11: Alcadia de Cali | K11: Contrato No. 4134.010.26.1.0441-2024 | L11: Kelly Carbonell | M11: Karen Arandia | N11: Carlos Sierra | O11: Simón Lopez | P11: Complete | Q11: N. A. | R11: 55117 - Fixed 55118 - Ret SW 55119 - CLOUD | S11: No Aplica
A12: P1908 | B12: P0255 | C12: =F12&" - "&D12&" - "&E12 -> AGA - Datalake Grupo de Energía de Bogotá - Cloud | D12: Datalake Grupo de Energía de Bogotá | E12: Cloud | F12: AGA | G12: Data | H12: =_xlfn.IFNA(VLOOKUP(F12,clientes!A:B,2,FALSE()),"--") -> Agata Data | I12: Inactivo | J12: Agata GEB- SDP | K12: Otrosi n° 3 Anexo 2 | L12: Kelly Carbonell | M12: Alejandra Gomez | N12: Carlos Sierra | O12: Jose Gallego | P12: Complete | Q12: N. A. | R12: 55120 - CLOUD 55121 - Ret SW 55122 - Ret | S12: No Aplica
A13: P1909 | B13: P0255 | C13: =F13&" - "&D13&" - "&E13 -> AGA - Datalake Grupo de Energía de Bogotá - Ret SW | D13: Datalake Grupo de Energía de Bogotá | E13: Ret SW | F13: AGA | G13: Software SW | H13: =_xlfn.IFNA(VLOOKUP(F13,clientes!A:B,2,FALSE()),"--") -> Agata Data | I13: Inactivo | J13: Agata GEB- SDP | K13: Otrosi n° 3 Anexo 2 | L13: Kelly Carbonell | M13: Alejandra Gomez | N13: Carlos Sierra | O13: Jose Gallego | P13: Complete | Q13: N. A. | R13: 55120 - CLOUD 55121 - Ret SW 55122 - Ret | S13: No Aplica
A14: P1910 | B14: P0255 | C14: =F14&" - "&D14&" - "&E14 -> AGA - Datalake Grupo de Energía de Bogotá - Ret | D14: Datalake Grupo de Energía de Bogotá | E14: Ret | F14: AGA | G14: Operación | H14: =_xlfn.IFNA(VLOOKUP(F14,clientes!A:B,2,FALSE()),"--") -> Agata Data | I14: Inactivo | J14: Agata GEB- SDP | K14: Anexo 2 GEB- SDP | L14: Kelly Carbonell | M14: Alejandra Gomez | N14: Carlos Sierra | O14: Jose Gallego | P14: Complete | Q14: N. A. | R14: 55120 - CLOUD 55121 - Ret SW 55122 - Ret | S14: Operations_Team_01
A15: P1911 | B15: P0321 | C15: =F15&" - "&D15&" - "&E15 -> AGR - CP Suite ( Smartcash) Operación - Ret | D15: CP Suite ( Smartcash) Operación | E15: Ret | F15: AGR | G15: Operación | H15: =_xlfn.IFNA(VLOOKUP(F15,clientes!A:B,2,FALSE()),"--") -> Fiduagraria | I15: Inactivo | J15: Fiduagraria- CP Suite | K15: OTROSI 3 CTO 032-2021. HIGH TECH | L15: Kelly Carbonell | M15: Alejandra Gomez | N15: Carlos Sierra | O15: Angel Villasmil | P15: Complete | Q15: Miguel.Carrillo | R15: 55123 | S15: Operations_Team_01
A16: P1912 | B16: P0339 | C16: =F16&" - "&D16&" - "&E16 -> AGR - Quicksight Operación 2025 - Cloud | D16: Quicksight Operación 2025 | E16: Cloud | F16: AGR | G16: Data | H16: =_xlfn.IFNA(VLOOKUP(F16,clientes!A:B,2,FALSE()),"--") -> Fiduagraria | I16: Inactivo | J16: Fiduagraria - Quicksight | K16: OTROSI 3 CTO 037-2021. HIGH TECH. | L16: Kelly Carbonell | M16: Alejandra Gomez | N16: Carlos Sierra | O16: Angel Villasmil | P16: Complete | Q16: N. A. | R16: 55124 | S16: No Aplica
A17: P1913 | B17: P0338 | C17: =F17&" - "&D17&" - "&E17 -> AGR - Snaptask Operación 2025 - Ret | D17: Snaptask Operación 2025 | E17: Ret | F17: AGR | G17: Operación | H17: =_xlfn.IFNA(VLOOKUP(F17,clientes!A:B,2,FALSE()),"--") -> Fiduagraria | I17: Inactivo | J17: Fiduagraria - Snaptask | K17: OTROSI 3 CTO 038-2021. HIGH TECH | L17: Kelly Carbonell | M17: Alejandra Gomez | N17: Carlos Sierra | O17: Angel Villasmil | P17: Complete | Q17: Miguel.Carrillo | R17: 55124 | S17: Operations_Team_01
A18: P1968 | B18: P0168 | C18: =F18&" - "&D18&" - "&E18 -> UBO - Operación Cloud - Cloud | D18: Operación Cloud | E18: Cloud | F18: UBO | G18: Data | H18: =_xlfn.IFNA(VLOOKUP(F18,clientes!A:B,2,FALSE()),"--") -> UBosque | I18: Activo | J18: Universidad del Bosque | K18: Cto PS 250-2021 | L18: David Cortes | M18: Alejandra Gomez | N18: Samuel Escobar | O18: N.A. | P18: In Progress | Q18: N. A. | R18: 55180 | S18: No Aplica | U18: Contrato UBO | W18: Ficha Tecnica - P0168 UBO Operación Cloud
A19: P1932 | B19: P0217 | C19: =F19&" - "&D19&" - "&E19 -> DIA - Aprovisionamiento multinube - Lote 3 - Cloud | D19: Aprovisionamiento multinube - Lote 3 | E19: Cloud | F19: DIA | G19: Data | H19: =_xlfn.IFNA(VLOOKUP(F19,clientes!A:B,2,FALSE()),"--") -> DIAN | I19: Activo | J19: Dian | K19: Convenio Contractual 92872-031-2022 | L19: Juan Bernal | M19: Ciliana Capera | N19: Nicolas Revollo | O19: Juan Sanchéz | P19: In Progress | Q19: N. A. | R19: 55144 | S19: Cloud Operations
A20: P1947 | B20: P0265 | C20: =F20&" - "&D20&" - "&E20 -> JPM - Cloud Managed Services 2023-25 - Ret | D20: Cloud Managed Services 2023-25 | E20: Ret | F20: JPM | G20: Operación | H20: =_xlfn.IFNA(VLOOKUP(F20,clientes!A:B,2,FALSE()),"--") -> JPMP - Justicia Penal Militar y Policial | I20: Activo | J20: Justicia Penal Militar | K20: OC 119973 | L20: David Cortes | M20: Marcela Sanchéz | N20: Nicolas Revollo | O20: Juan Sanchéz | P20: In Progress | Q20: N. A. | R20: 55159 - Ret 55160 - CLOUD | S20: Cloud Operations | U20: rfi_para_operacion_secundaria062022.docx | Y20: Kickoff JPMP OC 119973.pdf
A21: P1948 | B21: P0265 | C21: =F21&" - "&D21&" - "&E21 -> JPM - Cloud Managed Services 2023-25 - Cloud | D21: Cloud Managed Services 2023-25 | E21: Cloud | F21: JPM | G21: Data | H21: =_xlfn.IFNA(VLOOKUP(F21,clientes!A:B,2,FALSE()),"--") -> JPMP - Justicia Penal Militar y Policial | I21: Activo | J21: Justicia Penal Militar | K21: OC 119973 | L21: David Cortes | M21: Marcela Sanchéz | N21: Nicolas Revollo | O21: Juan Sanchéz | P21: In Progress | Q21: N. A. | R21: 55159 - Ret 55160 - CLOUD | S21: Cloud Operations | U21: rfi_para_operacion_secundaria062022.docx | Y21: Kickoff JPMP OC 119973.pdf
A22: P1918 | B22: P0302 | C22: =F22&" - "&D22&" - "&E22 -> BID - Migración y Diseño de Arquitectura AWS - Cloud | D22: Migración y Diseño de Arquitectura AWS | E22: Cloud | F22: BID | G22: Data | H22: =_xlfn.IFNA(VLOOKUP(F22,clientes!A:B,2,FALSE()),"--") -> Banco Interamericano de Desarrollo | I22: Inactivo | J22: Banco Interamericano de Desarrollo | K22: PURCHASE ORDER NO. 7000019059 | L22: Diana Castro | M22: Daniela Muñoz | N22: Carlos Sierra | P22: Complete | Q22: N. A. | R22: 55130 - CLOUD 55131 - Ret | S22: No Aplica
A23: P1919 | B23: P0302 | C23: =F23&" - "&D23&" - "&E23 -> BID - Migración y Diseño de Arquitectura AWS - Ret | D23: Migración y Diseño de Arquitectura AWS | E23: Ret | F23: BID | G23: Operación | H23: =_xlfn.IFNA(VLOOKUP(F23,clientes!A:B,2,FALSE()),"--") -> Banco Interamericano de Desarrollo | I23: Inactivo | J23: Banco Interamericano de Desarrollo | K23: PURCHASE ORDER NO. 7000019059 | L23: Diana Castro | M23: Daniela Muñoz | N23: Carlos Sierra | O23: Whitman Rojas | P23: Complete | Q23: N. A. | R23: 55130 - CLOUD 55131 - Ret | S23: Whitman Rojas
A24: P1933 | B24: P0280 | C24: =F24&" - "&D24&" - "&E24 -> DIA - Back Ups - Fixed | D24: Back Ups | E24: Fixed | F24: DIA | G24: Implementación | H24: =_xlfn.IFNA(VLOOKUP(F24,clientes!A:B,2,FALSE()),"--") -> DIAN | I24: Inactivo | J24: Dian | K24: Propuesta Backups | L24: Juan Bernal | M24: Ciliana Capera | N24: Nicolas Revollo | O24: Juan Sanchéz | P24: In Progress | Q24: N. A. | R24: 55145 | S24: Cloud Operations
A25: P1921 | B25: P0260 | C25: =F25&" - "&D25&" - "&E25 -> CAT - Nube Pública para Datalake - Ret | D25: Nube Pública para Datalake | E25: Ret | F25: CAT | G25: Operación | H25: =_xlfn.IFNA(VLOOKUP(F25,clientes!A:B,2,FALSE()),"--") -> Unidad Administrativa Especial de Catastro Distrital | I25: Inactivo | J25: Unidad Administrativa de Catastro | K25: OC 113430 | L25: Oscar Barragan | M25: Alejandra Gomez | N25: Carlos Sierra | O25: Marcelo Bonivento | P25: Complete | Q25: N. A. | R25: 55133 - Ret 55134 - CLOUD | S25: Cloud Operations
A26: P1922 | B26: P0260 | C26: =F26&" - "&D26&" - "&E26 -> CAT - Nube Pública para Datalake - Cloud | D26: Nube Pública para Datalake | E26: Cloud | F26: CAT | G26: Data | H26: =_xlfn.IFNA(VLOOKUP(F26,clientes!A:B,2,FALSE()),"--") -> Unidad Administrativa Especial de Catastro Distrital | I26: Inactivo | J26: Unidad Administrativa de Catastro | K26: OC 113430 | L26: Oscar Barragan | M26: Alejandra Gomez | N26: Carlos Sierra | O26: Marcelo Bonivento | P26: Complete | Q26: N. A. | R26: 55133 - Ret 55134 - CLOUD | S26: Cloud Operations
A27: P1923 | B27: P0281 | C27: =F27&" - "&D27&" - "&E27 -> CCC - IaaS para DRP - Cloud | D27: IaaS para DRP | E27: Cloud | F27: CCC | G27: Data | H27: =_xlfn.IFNA(VLOOKUP(F27,clientes!A:B,2,FALSE()),"--") -> Cámara de Comercio de Cali | I27: Activo | J27: Cámara de Comercio de Cali | K27: Contrato OSJ 2023-0374 | L27: Kelly Carbonell | M27: Angeline Lozada | N27: Nicolas Revollo | O27: Juan Sanchéz | P27: In Progress | Q27: N. A. | R27: 55135 | S27: Cloud Operations
A28: P1924 | B28: P0272 | C28: =F28&" - "&D28&" - "&E28 -> CSJ - Migración AWS - Fixed | D28: Migración AWS | E28: Fixed | F28: CSJ | G28: Implementación | H28: =_xlfn.IFNA(VLOOKUP(F28,clientes!A:B,2,FALSE()),"--") -> Consejo Superior de la Judicatura | I28: Inactivo | J28: Consejo Superior de la Judicatura | K28: OC 122576 | L28: David Cortes | M28: Andres Barrantes | N28: Nicolas Revollo | O28: Juan Sanchéz | P28: Complete | Q28: N. A. | R28: 55136 - Fixed 57148 - CLOUD | S28: Cloud Operations
A29: P1991 | B29: P0291 | C29: =F29&" - "&D29&" - "&E29 -> UNA - Unisalud - Ret | D29: Unisalud | E29: Ret | F29: UNA | G29: Operación | H29: =_xlfn.IFNA(VLOOKUP(F29,clientes!A:B,2,FALSE()),"--") -> Universidad Nacional de Colombia | I29: Activo | J29: Universidad Nacional | K29: NUVU - Proyectos - Documentos - 00. Administrativos - Todos los documentos | L29: Oscar Barragan | M29: Alejandra Gomez | N29: Nicolas Revollo | O29: Juan Sanchéz | P29: In Progress | Q29: N. A. | R29: 55203 | S29: No Aplica
A30: P1929 | B30: P0311 | C30: =F30&" - "&D30&" - "&E30 -> CJU - Sistema integrado de Secretaría Técnica - Ret | D30: Sistema integrado de Secretaría Técnica | E30: Ret | F30: CJU | G30: Operación | H30: =_xlfn.IFNA(VLOOKUP(F30,clientes!A:B,2,FALSE()),"--") -> Coljuegos | I30: Inactivo | J30: Coljuegos S.A | K30: CTO 323 - 2024 | L30: Juan Bernal | M30: Karen Arandia | N30: Moises Rojas | O30: Brandon Ardila | P30: Complete | Q30: N. A. | R30: 55140 - Fixed 55141 - Ret 55142 - Ret SW 55143 - CLOUD | S30: Brandon Ardila | U30: https://wgcp.sharepoint.com/:b:/s/NUVU-Proyectos/IQABo-cM_kQ9VrOfm--k8tbVAaRLttd3dWlyy9s53napM7A?e=UbppNX | V30: https://wgcp.sharepoint.com/:b:/s/NUVU-Proyectos/IQCBVOXbBT2DQIT79UziKQrLAa_SPAsIloWi8TYgz14jHl0?e=IAnuue
A31: P1994 | B31: P0294 | C31: =F31&" - "&D31&" - "&E31 -> UNA - Regalías Sikie - Cloud | D31: Regalías Sikie | E31: Cloud | F31: UNA | G31: Data | H31: =_xlfn.IFNA(VLOOKUP(F31,clientes!A:B,2,FALSE()),"--") -> Universidad Nacional de Colombia | I31: Activo | J31: Universidad Nacional | K31: NUVU - Proyectos - Documentos - 00. Administrativos - Todos los documentos | L31: Oscar Barragan | M31: Alejandra Gomez | N31: Nicolas Revollo | O31: Juan Sanchéz | P31: In Progress | Q31: N. A. | R31: 55206 | S31: No Aplica
A32: P2537 | B32: P0294 | C32: =F32&" - "&D32&" - "&E32 -> UNA - Regalías Sikie - Ret | D32: Regalías Sikie | E32: Ret | F32: UNA | G32: Operación | H32: =_xlfn.IFNA(VLOOKUP(F32,clientes!A:B,2,FALSE()),"--") -> Universidad Nacional de Colombia | I32: Activo | J32: Universida Nacional | K32: NUVU - Proyectos - Documentos - 00. Administrativos - Todos los documentos | L32: Oscar Barragan | M32: Alejandra Gomez | N32: Nicolas Revollo | O32: Juan Sanchéz | P32: In Progress | R32: 2600 | S32: Christyan Gutiérrez
A33: P2537 | B33: P0294 | C33: UNA - Regalías Sikie - Ret | D33: Regalías Sikie | E33: Ret | F33: UNA | G33: Operación | H33: =_xlfn.IFNA(VLOOKUP(F33,clientes!A:B,2,FALSE()),"--") -> Universidad Nacional de Colombia | I33: Activo | L33: Oscar Barragan | M33: Alejandra Gómez | P33: In Progress
A34: P1977 | B34: P0298 | C34: =F34&" - "&D34&" - "&E34 -> UNA - Fortinet - Fixed | D34: Fortinet | E34: Fixed | F34: UNA | G34: Implementación | H34: =_xlfn.IFNA(VLOOKUP(F34,clientes!A:B,2,FALSE()),"--") -> Universidad Nacional de Colombia | I34: Activo | J34: Universidad Nacional | K34: NUVU - Proyectos - Documentos - 00. Administrativos - Todos los documentos | L34: Oscar Barragan | M34: Alejandra Gomez | N34: Nicolas Revollo | O34: Juan Sanchéz | P34: In Progress | Q34: N. A. | R34: 55190 - Fixed 55191 - CLOUD | S34: Cloud Operations
A35: P1934 | B35: P0308 | C35: =F35&" - "&D35&" - "&E35 -> EAF - Portal Colombia Aprende - Fixed | D35: Portal Colombia Aprende | E35: Fixed | F35: EAF | G35: Implementación | H35: =_xlfn.IFNA(VLOOKUP(F35,clientes!A:B,2,FALSE()),"--") -> Universidad EAFIT - Escuela de Administración, Finanzas e Instituto Tecnológico | I35: Inactivo | J35: Universidad EAFIT | K35: CONTRATO HIGH TECH SOFTWARE VF Final | L35: Kelly Carbonell | M35: Karen Arandia | N35: Moises Rojas | O35: Brandon Ardila | P35: Complete | Q35: N. A. | R35: 55146 - Fixed 55147 - Ret SW 55148 - CLOUD | S35: Operations_Team_01
A36: P1935 | B36: P0308 | C36: =F36&" - "&D36&" - "&E36 -> EAF - Portal Colombia Aprende - Ret SW | D36: Portal Colombia Aprende | E36: Ret SW | F36: EAF | G36: Software SW | H36: =_xlfn.IFNA(VLOOKUP(F36,clientes!A:B,2,FALSE()),"--") -> Universidad EAFIT - Escuela de Administración, Finanzas e Instituto Tecnológico | I36: Inactivo | J36: Universidad EAFIT | K36: CONTRATO HIGH TECH SOFTWARE VF Final | L36: Kelly Carbonell | M36: Karen Arandia | N36: Moises Rojas | O36: Brandon Ardila | P36: Complete | Q36: N. A. | R36: 55146 - Fixed 55147 - Ret SW 55148 - CLOUD | S36: No Aplica
A37: P1936 | B37: P0308 | C37: =F37&" - "&D37&" - "&E37 -> EAF - Portal Colombia Aprende - Cloud | D37: Portal Colombia Aprende | E37: Cloud | F37: EAF | G37: Data | H37: =_xlfn.IFNA(VLOOKUP(F37,clientes!A:B,2,FALSE()),"--") -> Universidad EAFIT - Escuela de Administración, Finanzas e Instituto Tecnológico | I37: Inactivo | J37: Universidad EAFIT | K37: CONTRATO HIGH TECH SOFTWARE VF Final | L37: Kelly Carbonell | M37: Karen Arandia | N37: Moises Rojas | O37: Brandon Ardila | P37: Complete | Q37: N. A. | R37: 55146 - Fixed 55147 - Ret SW 55148 - CLOUD | S37: No Aplica
A38: P1978 | B38: P0298 | C38: =F38&" - "&D38&" - "&E38 -> UNA - Fortinet - Cloud | D38: Fortinet | E38: Cloud | F38: UNA | G38: Data | H38: =_xlfn.IFNA(VLOOKUP(F38,clientes!A:B,2,FALSE()),"--") -> Universidad Nacional de Colombia | I38: Activo | J38: Universidad Nacional | K38: NUVU - Proyectos - Documentos - 00. Administrativos - Todos los documentos | L38: Oscar Barragan | M38: Alejandra Gomez | N38: Nicolas Revollo | O38: Juan Sanchéz | P38: In Progress | Q38: N. A. | R38: 55190 - Fixed 55191 - CLOUD | S38: No Aplica
A39: P1938 | B39: P0317 | C39: =F39&" - "&D39&" - "&E39 -> FDN - Tableros BI - Fixed | D39: Tableros BI | E39: Fixed | F39: FDN | G39: Implementación | H39: =_xlfn.IFNA(VLOOKUP(F39,clientes!A:B,2,FALSE()),"--") -> Financiera de Desarrollo Nacional | I39: Inactivo | J39: FND | K39: Contrato 71 de 2024 | L39: David Cortes | M39: Jaime Grisales | N39: Carlos Sierra | O39: Juan Sanchéz | P39: Complete | Q39: N. A. | R39: 55155 | S39: Operations_Team_01
A40: P1939 | B40: P0290 | C40: =F40&" - "&D40&" - "&E40 -> FOA - Gestión Integral Mojana - Fixed | D40: Gestión Integral Mojana | E40: Fixed | F40: FOA | G40: Implementación | H40: =_xlfn.IFNA(VLOOKUP(F40,clientes!A:B,2,FALSE()),"--") -> Fondo Adaptación | I40: Inactivo | J40: Fondo Adaptación | K40: OC 126506 | L40: Juan Bernal | M40: Karen Arandia | N40: Carlos Sierra | O40: Diego Saavedra | P40: Complete | Q40: N. A. | R40: 55151 - Fixed 55152 - Ret SW 55153 - CLOUD | S40: Diego Saavedra
A41: P1940 | B41: P0290 | C41: =F41&" - "&D41&" - "&E41 -> FOA - Gestión Integral Mojana - Ret SW | D41: Gestión Integral Mojana | E41: Ret SW | F41: FOA | G41: Software SW | H41: =_xlfn.IFNA(VLOOKUP(F41,clientes!A:B,2,FALSE()),"--") -> Fondo Adaptación | I41: Inactivo | J41: Fondo Adaptación | K41: OC 126506 | L41: Juan Bernal | M41: Karen Arandia | N41: Carlos Sierra | O41: Diego Saavedra | P41: Complete | Q41: N. A. | R41: 55151 - Fixed 55152 - Ret SW 55153 - CLOUD | S41: No Aplica
A42: P1941 | B42: P0290 | C42: =F42&" - "&D42&" - "&E42 -> FOA - Gestión Integral Mojana - Cloud | D42: Gestión Integral Mojana | E42: Cloud | F42: FOA | G42: Data | H42: =_xlfn.IFNA(VLOOKUP(F42,clientes!A:B,2,FALSE()),"--") -> Fondo Adaptación | I42: Inactivo | J42: Fondo Adaptación | K42: OC 126506 | L42: Juan Bernal | M42: Karen Arandia | N42: Carlos Sierra | O42: Diego Saavedra | P42: Complete | Q42: N. A. | R42: 55151 - Fixed 55152 - Ret SW 55153 - CLOUD | S42: No Aplica
A43: P1942 | B43: P0075 | C43: =F43&" - "&D43&" - "&E43 -> GLO - SmartCash - Operación - Cloud | D43: SmartCash - Operación | E43: Cloud | F43: GLO | G43: Data | H43: =_xlfn.IFNA(VLOOKUP(F43,clientes!A:B,2,FALSE()),"--") -> Global Securities | I43: Inactivo | J43: Global Securities S.A | K43: Cto CP Suite | L43: Kelly Carbonell | M43: Alejandra Gomez | N43: Carlos Sierra | O43: Angel Villasmil | P43: Complete | Q43: Miguel.Carrillo | R43: 55154 | S43: No Aplica
A44: P1943 | B44: P0346 | C44: =F44&" - "&D44&" - "&E44 -> ICF - Evolución Datalake Fase1 2025 - Fixed | D44: Evolución Datalake Fase1 2025 | E44: Fixed | F44: ICF | G44: Implementación | H44: =_xlfn.IFNA(VLOOKUP(F44,clientes!A:B,2,FALSE()),"--") -> Instituto Colombiano Para La Evaluacion De La Educacion ICFES | I44: Inactivo | J44: Icfes | K44: OC 142744 | L44: Juan Bernal | M44: Ciliana Capera | N44: Moises Rojas | O44: Jairo Salas | P44: Complete | Q44: N. A. | R44: 55155 - Fixed 55156 - Ret 55157 - CLOUD 55158 - Ret SW | S44: Jairo Salas
A45: P1944 | B45: P0346 | C45: =F45&" - "&D45&" - "&E45 -> ICF - Evolución Datalake Fase1 2025 - Ret | D45: Evolución Datalake Fase1 2025 | E45: Ret | F45: ICF | G45: Operación | H45: =_xlfn.IFNA(VLOOKUP(F45,clientes!A:B,2,FALSE()),"--") -> Instituto Colombiano Para La Evaluacion De La Educacion ICFES | I45: Inactivo | J45: Icfes | K45: OC 142744 | L45: Juan Bernal | M45: Ciliana Capera | N45: Moises Rojas | O45: Jairo Salas | P45: Complete | Q45: N. A. | R45: 55155 - Fixed 55156 - Ret 55157 - CLOUD 55158 - Ret SW | S45: Jairo Salas
A46: P1945 | B46: P0346 | C46: =F46&" - "&D46&" - "&E46 -> ICF - Evolución Datalake Fase1 2025 - Cloud | D46: Evolución Datalake Fase1 2025 | E46: Cloud | F46: ICF | G46: Data | H46: =_xlfn.IFNA(VLOOKUP(F46,clientes!A:B,2,FALSE()),"--") -> Instituto Colombiano Para La Evaluacion De La Educacion ICFES | I46: Inactivo | J46: Icfes | K46: OC 142744 | L46: Juan Bernal | M46: Ciliana Capera | N46: Moises Rojas | O46: Jairo Salas | P46: Complete | Q46: N. A. | R46: 55155 - Fixed 55156 - Ret 55157 - CLOUD 55158 - Ret SW | S46: No Aplica
A47: P1946 | B47: P0346 | C47: =F47&" - "&D47&" - "&E47 -> ICF - Evolución Datalake Fase1 2025 - Ret SW | D47: Evolución Datalake Fase1 2025 | E47: Ret SW | F47: ICF | G47: Software SW | H47: =_xlfn.IFNA(VLOOKUP(F47,clientes!A:B,2,FALSE()),"--") -> Instituto Colombiano Para La Evaluacion De La Educacion ICFES | I47: Inactivo | J47: Icfes | K47: OC 142744 | L47: Juan Bernal | M47: Ciliana Capera | N47: Moises Rojas | O47: Jairo Salas | P47: Complete | Q47: N. A. | R47: 55155 - Fixed 55156 - Ret 55157 - CLOUD 55158 - Ret SW | S47: No Aplica
A48: P1983 | B48: P0300 | C48: =F48&" - "&D48&" - "&E48 -> UNA - Laboratorios Virtuales - Cloud | D48: Laboratorios Virtuales | E48: Cloud | F48: UNA | G48: Data | H48: =_xlfn.IFNA(VLOOKUP(F48,clientes!A:B,2,FALSE()),"--") -> Universidad Nacional de Colombia | I48: Activo | J48: Universidad Nacional | K48: OSE 90 4001 2024 SOL 20036 | L48: Oscar Barragan | M48: Alejandra Gomez | N48: Nicolas Revollo | O48: Juan Sanchéz | P48: Complete | Q48: N. A. | R48: 55195 | S48: Cloud Operations
A49: P1973 | B49: P0304 | C49: =F49&" - "&D49&" - "&E49 -> UNA - Editorial de UNAL - Cloud | D49: Editorial de UNAL | E49: Cloud | F49: UNA | G49: Data | H49: =_xlfn.IFNA(VLOOKUP(F49,clientes!A:B,2,FALSE()),"--") -> Universidad Nacional de Colombia | I49: Activo | J49: Universidad Nacional | K49: NUVU - Proyectos - 00. Administrativos - Todos los documentos | L49: Oscar Barragan | M49: Alejandra Gomez | N49: Nicolas Revollo | O49: Juan Sanchéz | P49: In Progress | Q49: N. A. | R49: 55185 | S49: No Aplica
A50: P1988 | B50: P0305 | C50: =F50&" - "&D50&" - "&E50 -> UNA - Repositorio - Cloud | D50: Repositorio | E50: Cloud | F50: UNA | G50: Data | H50: =_xlfn.IFNA(VLOOKUP(F50,clientes!A:B,2,FALSE()),"--") -> Universidad Nacional de Colombia | I50: Activo | J50: Universidad Nacional | K50: NUVU - Proyectos - Documentos - 00. Administrativos - Todos los documentos | L50: Oscar Barragan | M50: Alejandra Gomez | N50: Nicolas Revollo | O50: Juan Sanchéz | P50: In Progress | Q50: N. A. | R50: 55200 | S50: No Aplica
A51: P1982 | B51: P0306 | C51: =F51&" - "&D51&" - "&E51 -> UNA - HPC Registro y Matrícula - Cloud | D51: HPC Registro y Matrícula | E51: Cloud | F51: UNA | G51: Data | H51: =_xlfn.IFNA(VLOOKUP(F51,clientes!A:B,2,FALSE()),"--") -> Universidad Nacional de Colombia | I51: Activo | J51: Universidad Nacional | K51: NUVU - Proyectos - 00. Administrativo - Todos los documentos | L51: Oscar Barragan | M51: Alejandra Gomez | N51: Nicolas Revollo | O51: Juan Sanchéz | P51: In Progress | Q51: N. A. | R51: 55194 | S51: No Aplica
A52: P1951 | B52: P0316 | C52: =F52&" - "&D52&" - "&E52 -> MTC - Ciudades y territorios inteligentes Mintic - Ret | D52: Ciudades y territorios inteligentes Mintic | E52: Ret | F52: MTC | G52: Operación | H52: =_xlfn.IFNA(VLOOKUP(F52,clientes!A:B,2,FALSE()),"--") -> MinTic | I52: Inactivo | J52: Mintic | K52: NUVU - Proyectos - 01. Habilitacion - Todos los documentos | L52: Diana Rojas | M52: Karen Arandia | N52: Nicolas Revollo | O52: Juan Sanchéz | P52: Complete | Q52: N. A. | R52: 55163 - Ret 55164 - Fixed 55165 - CLOUD | S52: Operations_Team_01
A53: P1952 | B53: P0316 | C53: =F53&" - "&D53&" - "&E53 -> MTC - Ciudades y territorios inteligentes Mintic - Fixed | D53: Ciudades y territorios inteligentes Mintic | E53: Fixed | F53: MTC | G53: Implementación | H53: =_xlfn.IFNA(VLOOKUP(F53,clientes!A:B,2,FALSE()),"--") -> MinTic | I53: Inactivo | J53: Mintic | K53: NUVU - Proyectos - 01. Habilitacion - Todos los documentos | L53: Diana Rojas | M53: Karen Arandia | N53: Nicolas Revollo | O53: Juan Sanchéz | P53: Complete | Q53: N. A. | R53: 55163 - Ret 55164 - Fixed 55165 - CLOUD | S53: Cloud Operations
A54: P1953 | B54: P0316 | C54: =F54&" - "&D54&" - "&E54 -> MTC - Ciudades y territorios inteligentes Mintic - Cloud | D54: Ciudades y territorios inteligentes Mintic | E54: Cloud | F54: MTC | G54: Data | H54: =_xlfn.IFNA(VLOOKUP(F54,clientes!A:B,2,FALSE()),"--") -> MinTic | I54: Inactivo | J54: Mintic | K54: NUVU - Proyectos - 01. Habilitacion - Todos los documentos | L54: Diana Rojas | M54: Karen Arandia | N54: Nicolas Revollo | O54: Juan Sanchéz | P54: Complete | Q54: N. A. | R54: 55163 - Ret 55164 - Fixed 55165 - CLOUD | S54: No Aplica
A55: P1954 | B55: P0309 | C55: =F55&" - "&D55&" - "&E55 -> MTC - Microcentros AI - Ret | D55: Microcentros AI | E55: Ret | F55: MTC | G55: Operación | H55: =_xlfn.IFNA(VLOOKUP(F55,clientes!A:B,2,FALSE()),"--") -> MinTic | I55: Inactivo | J55: Mintic | K55: NUVU - Proyectos - Documentos - 01. Documentación Esencial - Todos los documentos | L55: Diana Rojas | M55: Karen Arandia | N55: Carlos Sierra | O55: Jose Gallego | P55: Complete | Q55: N. A. | R55: 55166 - Ret 55167 - CLOUD | S55: Operations_Team_01
A56: P1955 | B56: P0309 | C56: =F56&" - "&D56&" - "&E56 -> MTC - Microcentros AI - Cloud | D56: Microcentros AI | E56: Cloud | F56: MTC | G56: Data | H56: =_xlfn.IFNA(VLOOKUP(F56,clientes!A:B,2,FALSE()),"--") -> MinTic | I56: Inactivo | J56: Mintic | K56: NUVU - Proyectos - Documentos - 01. Documentación Esencial - Todos los documentos | L56: Diana Rojas | M56: Karen Arandia | N56: Carlos Sierra | O56: Jose Gallego | P56: Complete | Q56: N. A. | R56: 55166 - Ret 55167 - CLOUD | S56: No Aplica
A57: P1959 | B57: P0301 | C57: =F57&" - "&D57&" - "&E57 -> SAN - Soporte y Mantenimiento Quipu 2024-25 - Ret | D57: Soporte y Mantenimiento Quipu 2024-25 | E57: Ret | F57: SAN | G57: Operación | H57: =_xlfn.IFNA(VLOOKUP(F57,clientes!A:B,2,FALSE()),"--") -> Sanidad | I57: Inactivo | J57: Dirección de Sanidad | K57: Contrato 07-7-20157-24 | L57: Juan Bernal | M57: Marcela Sanchéz | N57: Juan Zambrano | O57: Gersón Pineda | P57: Complete | Q57: David.Gomez | R57: 55171 | S57: Operations_Team_01
A58: P1960 | B58: P0307 | C58: =F58&" - "&D58&" - "&E58 -> SDH - Datalake Secretaria del Hábitat - Ret SW | D58: Datalake Secretaria del Hábitat | E58: Ret SW | F58: SDH | G58: Software SW | H58: =_xlfn.IFNA(VLOOKUP(F58,clientes!A:B,2,FALSE()),"--") -> Secretaria Distrital del Hábitat | I58: Inactivo | J58: Secretaria Distrital del Hábitat | K58: Contrato No 1558-2024 | L58: David Cortes | M58: Alejandra Gomez | N58: Moises Rojas | O58: Jairo Salas | P58: Complete | Q58: N. A. | R58: 55172 - Ret SW 55173 - CLOUD 55174 - Ret | S58: No Aplica
A59: P1961 | B59: P0307 | C59: =F59&" - "&D59&" - "&E59 -> SDH - Datalake Secretaria del Hábitat - Cloud | D59: Datalake Secretaria del Hábitat | E59: Cloud | F59: SDH | G59: Data | H59: =_xlfn.IFNA(VLOOKUP(F59,clientes!A:B,2,FALSE()),"--") -> Secretaria Distrital del Hábitat | I59: Inactivo | J59: Secretaria Distrital del Hábitat | K59: Contrato No 1558-2024 | L59: David Cortes | M59: Alejandra Gomez | N59: Moises Rojas | O59: Jairo Salas | P59: Complete | Q59: N. A. | R59: 55172 - Ret SW 55173 - CLOUD 55174 - Ret | S59: No Aplica
A60: P1962 | B60: P0307 | C60: =F60&" - "&D60&" - "&E60 -> SDH - Datalake Secretaria del Hábitat - Ret | D60: Datalake Secretaria del Hábitat | E60: Ret | F60: SDH | G60: Operación | H60: =_xlfn.IFNA(VLOOKUP(F60,clientes!A:B,2,FALSE()),"--") -> Secretaria Distrital del Hábitat | I60: Inactivo | J60: Secretaria Distrital del Hábitat | K60: Contrato No 1558-2024 | L60: David Cortes | M60: Alejandra Gomez | N60: Moises Rojas | O60: Jairo Salas | P60: Complete | Q60: N. A. | R60: 55172 - Ret SW 55173 - CLOUD 55174 - Ret | S60: Operations_Team_01
A61: P1963 | B61: P0332 | C61: =F61&" - "&D61&" - "&E61 -> SOC - IA Sociedades 2024-2025 - Cloud | D61: IA Sociedades 2024-2025 | E61: Cloud | F61: SOC | G61: Data | H61: =_xlfn.IFNA(VLOOKUP(F61,clientes!A:B,2,FALSE()),"--") -> Superintendencia de Sociedades | I61: Inactivo | J61: Supersociedades | K61: OC139384 00. Administrativo | L61: Daniel Sebastian Vargas | M61: Marcela Sanchéz | N61: Carlos Sierra | O61: Ariane Hernandez | P61: Complete | Q61: Miguel.Carrillo | R61: 55175 - CLOUD 55176 - Ret | S61: No Aplica
A62: P1964 | B62: P0332 | C62: =F62&" - "&D62&" - "&E62 -> SOC - IA Sociedades 2024-2025 - Ret | D62: IA Sociedades 2024-2025 | E62: Ret | F62: SOC | G62: Operación | H62: =_xlfn.IFNA(VLOOKUP(F62,clientes!A:B,2,FALSE()),"--") -> Superintendencia de Sociedades | I62: Inactivo | J62: Supersociedades | K62: OC139384 00. Administrativo | L62: Daniel Sebastian Vargas | M62: Marcela Sanchéz | N62: Carlos Sierra | O62: Ariane Hernandez | P62: Complete | Q62: Miguel.Carrillo | R62: 55175 - CLOUD 55176 - Ret | S62: Operations_Team_01
A63: P1928 | B63: P0311 | C63: =F63&" - "&D63&" - "&E63 -> CJU - Sistema integrado de Secretaría Técnica - Fixed | D63: Sistema integrado de Secretaría Técnica | E63: Fixed | F63: CJU | G63: Implementación | H63: =_xlfn.IFNA(VLOOKUP(F63,clientes!A:B,2,FALSE()),"--") -> Coljuegos | I63: Inactivo | J63: Coljuegos S.A | K63: CTO 323 - 2024 | L63: Juan Bernal | M63: Karen Arandia | N63: Moises Rojas | O63: Brandon Ardila | P63: In Progress | Q63: N. A. | R63: 55140 - Fixed 55141 - Ret 55142 - Ret SW 55143 - CLOUD | S63: Brandon Ardila | U63: https://wgcp.sharepoint.com/:b:/s/NUVU-Proyectos/IQABo-cM_kQ9VrOfm--k8tbVAaRLttd3dWlyy9s53napM7A?e=UbppNX | V63: https://wgcp.sharepoint.com/:b:/s/NUVU-Proyectos/IQCBVOXbBT2DQIT79UziKQrLAa_SPAsIloWi8TYgz14jHl0?e=IAnuue
A64: P1930 | B64: P0311 | C64: =F64&" - "&D64&" - "&E64 -> CJU - Sistema integrado de Secretaría Técnica - Ret SW | D64: Sistema integrado de Secretaría Técnica | E64: Ret SW | F64: CJU | G64: Software SW | H64: =_xlfn.IFNA(VLOOKUP(F64,clientes!A:B,2,FALSE()),"--") -> Coljuegos | I64: Inactivo | J64: Coljuegos S.A | K64: CTO 323 - 2024 | L64: Juan Bernal | M64: Karen Arandia | N64: Moises Rojas | O64: Brandon Ardila | P64: In Progress | Q64: N. A. | R64: 55140 - Fixed 55141 - Ret 55142 - Ret SW 55143 - CLOUD | S64: No Aplica | U64: https://wgcp.sharepoint.com/:b:/s/NUVU-Proyectos/IQABo-cM_kQ9VrOfm--k8tbVAaRLttd3dWlyy9s53napM7A?e=UbppNX | V64: https://wgcp.sharepoint.com/:b:/s/NUVU-Proyectos/IQCBVOXbBT2DQIT79UziKQrLAa_SPAsIloWi8TYgz14jHl0?e=IAnuue
A65: P1931 | B65: P0311 | C65: =F65&" - "&D65&" - "&E65 -> CJU - Sistema integrado de Secretaría Técnica - Cloud | D65: Sistema integrado de Secretaría Técnica | E65: Cloud | F65: CJU | G65: Data | H65: =_xlfn.IFNA(VLOOKUP(F65,clientes!A:B,2,FALSE()),"--") -> Coljuegos | I65: Inactivo | J65: Coljuegos S.A | K65: CTO 323 - 2024 | L65: Juan Bernal | M65: Karen Arandia | N65: Moises Rojas | O65: Brandon Ardila | P65: In Progress | Q65: N. A. | R65: 55140 - Fixed 55141 - Ret 55142 - Ret SW 55143 - CLOUD | S65: No Aplica | U65: https://wgcp.sharepoint.com/:b:/s/NUVU-Proyectos/IQABo-cM_kQ9VrOfm--k8tbVAaRLttd3dWlyy9s53napM7A?e=UbppNX | V65: https://wgcp.sharepoint.com/:b:/s/NUVU-Proyectos/IQCBVOXbBT2DQIT79UziKQrLAa_SPAsIloWi8TYgz14jHl0?e=IAnuue
A66: P1937 | B66: P0318 | C66: =F66&" - "&D66&" - "&E66 -> FDN - Servicios profesionales Arquitectura - Fixed | D66: Servicios profesionales Arquitectura | E66: Fixed | F66: FDN | G66: Implementación | H66: =_xlfn.IFNA(VLOOKUP(F66,clientes!A:B,2,FALSE()),"--") -> Financiera de Desarrollo Nacional | I66: Inactivo | J66: FND | K66: Pedido 4402419 HIGH TECH SOFTWARE SAS | L66: David Cortes | M66: Alejandra Gomez | N66: Nicolas Revollo | O66: Juan Sanchéz | P66: In Progress | Q66: N. A. | R66: 55149 - Fixed | S66: Operations_Team_01 | T66: Contrato | U66: Contrato FDN | Y66: KO FNA
A67: P1969 | B67: P0322 | C67: =F67&" - "&D67&" - "&E67 -> UCA - ODS 1512 - Soporte y Mtto Quipu 24-25 - Ret | D67: ODS 1512 - Soporte y Mtto Quipu 24-25 | E67: Ret | F67: UCA | G67: Operación | H67: =_xlfn.IFNA(VLOOKUP(F67,clientes!A:B,2,FALSE()),"--") -> Universidad de Caldas | I67: Inactivo | J67: Universidad de Caldas | K67: ODS 1512-2024 | L67: Kelly Carbonell | M67: Alejandra Gomez | N67: Carlos Sierra | O67: Sebastian Vidal | P67: Complete | Q67: Valentina.Salazar | R67: 55181 | S67: Operations_Team_UCA
A68: P1949 | B68: P0320 | C68: =F68&" - "&D68&" - "&E68 -> MMN - Cloud Sistema de Recaudo - Fixed | D68: Cloud Sistema de Recaudo | E68: Fixed | F68: MMN | G68: Implementación | H68: =_xlfn.IFNA(VLOOKUP(F68,clientes!A:B,2,FALSE()),"--") -> Empresa De Transporte Masivo Del Valle De Aburrá Limitada | I68: Activo | J68: Metro de Medellín | K68: 01. Documentación esencial | L68: Diana Rojas | M68: Daniela Muñoz | N68: Nicolas Revollo | O68: Juan Sanchéz | P68: In Progress | Q68: N. A. | R68: 55161 - Fixed 55162 - CLOUD | S68: Cloud Operations | W68: https://wgcp.sharepoint.com/:x:/r/sites/NUVU-Proyectos/_layouts/15/Doc.aspx?sourcedoc=%7B50D14C49-2031-4558-9BEC-B6C4F9628641%7D&file=Dimensionamiento%20y%20costos%20-%20Metro%20Medellin%20-%20Copia.xlsx&action=default&mobileredirect=true
A69: P1950 | B69: P0320 | C69: =F69&" - "&D69&" - "&E69 -> MMN - Cloud Sistema de Recaudo - Cloud | D69: Cloud Sistema de Recaudo | E69: Cloud | F69: MMN | G69: Data | H69: =_xlfn.IFNA(VLOOKUP(F69,clientes!A:B,2,FALSE()),"--") -> Empresa De Transporte Masivo Del Valle De Aburrá Limitada | I69: Activo | J69: Metro de Medellín | K69: 01. Documentación esencial | L69: Diana Rojas | M69: Daniela Muñoz | N69: Nicolas Revollo | O69: Juan Sanchéz | P69: In Progress | Q69: N. A. | R69: 55161 - Fixed 55162 - CLOUD | S69: No Aplica | W69: https://wgcp.sharepoint.com/:x:/r/sites/NUVU-Proyectos/_layouts/15/Doc.aspx?sourcedoc=%7B50D14C49-2031-4558-9BEC-B6C4F9628641%7D&file=Dimensionamiento%20y%20costos%20-%20Metro%20Medellin%20-%20Copia.xlsx&action=default&mobileredirect=true
A70: P2225 | B70: P0320 | C70: =F70&" - "&D70&" - "&E70 -> MMN - Cloud Sistema de Recaudo - Ret Other Vendors | D70: Cloud Sistema de Recaudo | E70: Ret Other Vendors | F70: MMN | G70: Operación | H70: =_xlfn.IFNA(VLOOKUP(F70,clientes!A:B,2,FALSE()),"--") -> Empresa De Transporte Masivo Del Valle De Aburrá Limitada | I70: Activo | J70: Metro de Medellín | K70: 01. Documentación esencial | L70: Diana Rojas | M70: Daniela Muñoz | N70: Nicolas Revollo | O70: Juan Sanchéz | P70: In Progress | Q70: N. A. | R70: 67635 - Other Vendor | S70: No Aplica | W70: https://wgcp.sharepoint.com/:x:/r/sites/NUVU-Proyectos/_layouts/15/Doc.aspx?sourcedoc=%7B50D14C49-2031-4558-9BEC-B6C4F9628641%7D&file=Dimensionamiento%20y%20costos%20-%20Metro%20Medellin%20-%20Copia.xlsx&action=default&mobileredirect=true
A71: P2310 | B71: P0320 | C71: =F71&" - "&D71&" - "&E71 -> MMN - Cloud Sistema de Recaudo - Ret | D71: Cloud Sistema de Recaudo | E71: Ret | F71: MMN | G71: Operación | H71: =_xlfn.IFNA(VLOOKUP(F71,clientes!A:B,2,FALSE()),"--") -> Empresa De Transporte Masivo Del Valle De Aburrá Limitada | I71: Activo | J71: Metro de Medellín | K71: 01. Documentación esencial | L71: Diana Rojas | M71: Daniela Muñoz | N71: Nicolas Revollo | O71: Juan Sanchéz | P71: In Progress | Q71: N. A. | R71: 70411 - Ret | S71: No Aplica | W71: https://wgcp.sharepoint.com/:x:/r/sites/NUVU-Proyectos/_layouts/15/Doc.aspx?sourcedoc=%7B50D14C49-2031-4558-9BEC-B6C4F9628641%7D&file=Dimensionamiento%20y%20costos%20-%20Metro%20Medellin%20-%20Copia.xlsx&action=default&mobileredirect=true
A72: P1965 | B72: P0334 | C72: =F72&" - "&D72&" - "&E72 -> SPD - Repositorio Único de Datos - Fixed | D72: Repositorio Único de Datos | E72: Fixed | F72: SPD | G72: Implementación | H72: =_xlfn.IFNA(VLOOKUP(F72,clientes!A:B,2,FALSE()),"--") -> Superintendencia Servicios Públicos Domiciliarios | I72: Inactivo | J72: Superservicios | K72: PO-140333_v1_20241227 | L72: Miguel Garcia | M72: Ciliana Capera | N72: Moises Rojas | O72: Santiago Villegas | P72: In Progress | Q72: N. A. | R72: 55177 - Fixed 55178 - Ret SW 55179 - CLOUD | S72: Santiago Villegas
A73: P1966 | B73: P0334 | C73: =F73&" - "&D73&" - "&E73 -> SPD - Repositorio Único de Datos - Ret SW | D73: Repositorio Único de Datos | E73: Ret SW | F73: SPD | G73: Software SW | H73: =_xlfn.IFNA(VLOOKUP(F73,clientes!A:B,2,FALSE()),"--") -> Superintendencia Servicios Públicos Domiciliarios | I73: Activo | J73: Superservicios | K73: PO-140333_v1_20241227 | L73: Miguel Garcia | M73: Ciliana Capera | N73: Moises Rojas | O73: Santiago Villegas | P73: In Progress | Q73: N. A. | R73: 55177 - Fixed 55178 - Ret SW 55179 - CLOUD | S73: No Aplica
A74: P1967 | B74: P0334 | C74: =F74&" - "&D74&" - "&E74 -> SPD - Repositorio Único de Datos - Cloud | D74: Repositorio Único de Datos | E74: Cloud | F74: SPD | G74: Data | H74: =_xlfn.IFNA(VLOOKUP(F74,clientes!A:B,2,FALSE()),"--") -> Superintendencia Servicios Públicos Domiciliarios | I74: Activo | J74: Superservicios | K74: PO-140333_v1_20241227 | L74: Miguel Garcia | M74: Ciliana Capera | N74: Moises Rojas | O74: Santiago Villegas | P74: In Progress | Q74: N. A. | R74: 55177 - Fixed 55178 - Ret SW 55179 - CLOUD | S74: Santiago Villegas
A75: P1979 | B75: P0336 | C75: =F75&" - "&D75&" - "&E75 -> UNA - Gestión de Información - Fixed | D75: Gestión de Información | E75: Fixed | F75: UNA | G75: Implementación | H75: =_xlfn.IFNA(VLOOKUP(F75,clientes!A:B,2,FALSE()),"--") -> Universidad Nacional de Colombia | I75: Activo | J75: Universida Nacional | K75: NUVU - Proyectos - Documentos - 00. Administrativo - Todos los documentos | L75: Oscar Barragan | M75: Alejandra Gomez | N75: Nicolas Revollo | O75: Juan Sanchéz | P75: In Progress | Q75: N. A. | R75: 55191 - Fixed 55192 - Ret 55193 - CLOUD | S75: Cloud Operations
A76: P1980 | B76: P0336 | C76: =F76&" - "&D76&" - "&E76 -> UNA - Gestión de Información - Ret | D76: Gestión de Información | E76: Ret | F76: UNA | G76: Operación | H76: =_xlfn.IFNA(VLOOKUP(F76,clientes!A:B,2,FALSE()),"--") -> Universidad Nacional de Colombia | I76: Activo | J76: Universida Nacional | K76: NUVU - Proyectos - Documentos - 00. Administrativo - Todos los documentos | L76: Oscar Barragan | M76: Alejandra Gomez | N76: Nicolas Revollo | O76: Juan Sanchéz | P76: In Progress | Q76: N. A. | R76: 55191 - Fixed 55192 - Ret 55193 - CLOUD | S76: Cloud Operations
A77: P1981 | B77: P0336 | C77: =F77&" - "&D77&" - "&E77 -> UNA - Gestión de Información - Cloud | D77: Gestión de Información | E77: Cloud | F77: UNA | G77: Data | H77: =_xlfn.IFNA(VLOOKUP(F77,clientes!A:B,2,FALSE()),"--") -> Universidad Nacional de Colombia | I77: Activo | J77: Universida Nacional | K77: NUVU - Proyectos - Documentos - 00. Administrativo - Todos los documentos | L77: Oscar Barragan | M77: Alejandra Gomez | N77: Nicolas Revollo | O77: Juan Sanchéz | P77: In Progress | Q77: N. A. | R77: 55191 - Fixed 55192 - Ret 55193 - CLOUD | S77: No Aplica
A78: P1989 | B78: P0330 | C78: =F78&" - "&D78&" - "&E78 -> UNA - Servicios Quipu - Fixed | D78: Servicios Quipu | E78: Fixed | F78: UNA | G78: Implementación | H78: =_xlfn.IFNA(VLOOKUP(F78,clientes!A:B,2,FALSE()),"--") -> Universidad Nacional de Colombia | I78: Inactivo | J78: Universidad Nacional | K78: OEF 3 | L78: Oscar Barragan | M78: Alejandra Gomez | N78: Carlos Sierra | O78: Angel Villasmil | P78: Complete | Q78: N. A. | R78: 55201 | S78: Operations_Team_01
A79: P1975 | B79: P0340 | C79: =F79&" - "&D79&" - "&E79 -> UNA - Facultad de ingenieria - Ret | D79: Facultad de ingenieria | E79: Ret | F79: UNA | G79: Operación | H79: =_xlfn.IFNA(VLOOKUP(F79,clientes!A:B,2,FALSE()),"--") -> Universidad Nacional de Colombia | I79: Activo | J79: Universidad Nacional | K79: NUVU - Proyectos - Documentos - 00. Administrativos - Todos los documentos | L79: Oscar Barragan | M79: Alejandra Gomez | N79: Nicolas Revollo | O79: Juan Sanchéz | P79: In Progress | Q79: N. A. | S79: Cloud Operations
A80: P2036 | B80: P0340 | C80: =F80&" - "&D80&" - "&E80 -> UNA - Facultad de ingenieria - Cloud | D80: Facultad de ingenieria | E80: Cloud | F80: UNA | G80: Data | H80: =_xlfn.IFNA(VLOOKUP(F80,clientes!A:B,2,FALSE()),"--") -> Universidad Nacional de Colombia | I80: Activo | J80: Universidad Nacional | K80: NUVU - Proyectos - Documentos - 00. Administrativos - Todos los documentos | L80: Oscar Barragan | M80: Alejandra Gomez | N80: Nicolas Revollo | O80: Juan Sanchéz | P80: In Progress | Q80: N. A.
A81: P1914 | B81: P0341 | C81: =F81&" - "&D81&" - "&E81 -> BID - Development as a Service - Fixed | D81: Development as a Service | E81: Fixed | F81: BID | G81: Implementación | H81: =_xlfn.IFNA(VLOOKUP(F81,clientes!A:B,2,FALSE()),"--") -> Banco Interamericano de Desarrollo | I81: Activo | J81: Banco Interamericano de Desarrollo | K81: PO 7000020361 & PO 7000021280 | L81: Diana Castro | M81: Marcela Sanchéz | N81: Carlos Sierra | O81: Whitman Rojas | P81: In Progress | Q81: N. A. | R81: 55126 - Fixed 55127 - Ret 55128 - CLOUD 55129 - Ret SW | S81: Whitman Rojas | U81: https://wgcp.sharepoint.com/:b:/s/NUVU-Proyectos/IQAS_CUjms1cU1B-YPPgYqMBAcu3G3Wrw6gNMmM_M5Y27a0?e=O0w4aL | V81: https://wgcp.sharepoint.com/:b:/s/NUVU-Proyectos/IQBjfBAQLcnyUr3C8FIhl4EBAbp8TvYSDZoiHeWWAE0Pa3U?e=slDQDX
A82: P1992 | B82: P0181 | C82: =F82&" - "&D82&" - "&E82 -> WIT - Witty Operación - Ret | D82: Witty Operación | E82: Ret | F82: WIT | G82: Operación | H82: =_xlfn.IFNA(VLOOKUP(F82,clientes!A:B,2,FALSE()),"--") -> Witty | I82: Inactivo | J82: Inversiones Kappi S.A.S | K82: Contrato operación Kappi | M82: Daniela Muñoz | N82: Carlos Sierra | O82: Angel Villasmil | P82: Complete | Q82: Carlos.Aroca | R82: 55204 | S82: Operations_Team_01
A83: P1993 | B83: P0296 | C83: =F83&" - "&D83&" - "&E83 -> SIC - Soporte infraestructura - Ret | D83: Soporte infraestructura | E83: Ret | F83: SIC | G83: Operación | H83: =_xlfn.IFNA(VLOOKUP(F83,clientes!A:B,2,FALSE()),"--") -> Superintendencia de Industria y Comercio | I83: Inactivo | J83: SIC | K83: OC 128682 | L83: Juan Bernal | M83: Marcela Sanchéz | N83: Carlos Sierra | O83: Gustavo Galvis | P83: Complete | Q83: Carlos.Aroca | R83: 55205 | S83: No Aplica
A84: P1915 | B84: P0341 | C84: =F84&" - "&D84&" - "&E84 -> BID - Development as a Service - Ret | D84: Development as a Service | E84: Ret | F84: BID | G84: Operación | H84: =_xlfn.IFNA(VLOOKUP(F84,clientes!A:B,2,FALSE()),"--") -> Banco Interamericano de Desarrollo | I84: Activo | J84: Banco Interamericano de Desarrollo | K84: PO 7000020361 & PO 7000021280 | L84: Diana Castro | M84: Marcela Sanchéz | N84: Carlos Sierra | O84: Whitman Rojas | P84: In Progress | Q84: N. A. | R84: 55126 - Fixed 55127 - Ret 55128 - CLOUD 55129 - Ret SW | S84: Whitman Rojas | U84: https://wgcp.sharepoint.com/:b:/s/NUVU-Proyectos/IQAS_CUjms1cU1B-YPPgYqMBAcu3G3Wrw6gNMmM_M5Y27a0?e=O0w4aL | V84: https://wgcp.sharepoint.com/:b:/s/NUVU-Proyectos/IQBjfBAQLcnyUr3C8FIhl4EBAbp8TvYSDZoiHeWWAE0Pa3U?e=slDQDX
A85: P1916 | B85: P0341 | C85: =F85&" - "&D85&" - "&E85 -> BID - Development as a Service - Cloud | D85: Development as a Service | E85: Cloud | F85: BID | G85: Data | H85: =_xlfn.IFNA(VLOOKUP(F85,clientes!A:B,2,FALSE()),"--") -> Banco Interamericano de Desarrollo | I85: Activo | J85: Banco Interamericano de Desarrollo | K85: PO 7000020361 & PO 7000021280 | L85: Diana Castro | M85: Marcela Sanchéz | N85: Carlos Sierra | O85: Whitman Rojas | P85: In Progress | Q85: N. A. | R85: 55126 - Fixed 55127 - Ret 55128 - CLOUD 55129 - Ret SW | S85: No Aplica | U85: https://wgcp.sharepoint.com/:b:/s/NUVU-Proyectos/IQAS_CUjms1cU1B-YPPgYqMBAcu3G3Wrw6gNMmM_M5Y27a0?e=O0w4aL | V85: https://wgcp.sharepoint.com/:b:/s/NUVU-Proyectos/IQBjfBAQLcnyUr3C8FIhl4EBAbp8TvYSDZoiHeWWAE0Pa3U?e=slDQDX
A86: P1917 | B86: P0341 | C86: =F86&" - "&D86&" - "&E86 -> BID - Development as a Service - Ret SW | D86: Development as a Service | E86: Ret SW | F86: BID | G86: Software SW | H86: =_xlfn.IFNA(VLOOKUP(F86,clientes!A:B,2,FALSE()),"--") -> Banco Interamericano de Desarrollo | I86: Activo | J86: Banco Interamericano de Desarrollo | K86: PO 7000020361 & PO 7000021280 | L86: Diana Castro | M86: Marcela Sanchéz | N86: Carlos Sierra | O86: Whitman Rojas | P86: In Progress | Q86: N. A. | R86: 55126 - Fixed 55127 - Ret 55128 - CLOUD 55129 - Ret SW | S86: No Aplica | U86: https://wgcp.sharepoint.com/:b:/s/NUVU-Proyectos/IQAS_CUjms1cU1B-YPPgYqMBAcu3G3Wrw6gNMmM_M5Y27a0?e=O0w4aL | V86: https://wgcp.sharepoint.com/:b:/s/NUVU-Proyectos/IQBjfBAQLcnyUr3C8FIhl4EBAbp8TvYSDZoiHeWWAE0Pa3U?e=slDQDX
A87: P2030 | B87: P0343 | C87: =F87&" - "&D87&" - "&E87 -> FDN - Servicios de arquitectura - Cloud | D87: Servicios de arquitectura | E87: Cloud | F87: FDN | G87: Data | H87: =_xlfn.IFNA(VLOOKUP(F87,clientes!A:B,2,FALSE()),"--") -> Financiera de Desarrollo Nacional | I87: Activo | J87: FND | K87: Pedido 4402476 | L87: David Cortes | M87: Alejandra Gomez | N87: Nicolas Revollo | O87: Juan Sanchéz | P87: In Progress | Q87: N. A. | R87: 57152 - CLOUD | S87: No Aplica | T87: Contrato | U87: Contrato FDN | Y87: KO FNA
A88: P1990 | B88: P0344 | C88: =F88&" - "&D88&" - "&E88 -> UNA - Soporte y Mtto Quipu 2025 - Ret | D88: Soporte y Mtto Quipu 2025 | E88: Ret | F88: UNA | G88: Operación | H88: =_xlfn.IFNA(VLOOKUP(F88,clientes!A:B,2,FALSE()),"--") -> Universidad Nacional de Colombia | I88: Activo | J88: Universidad Nacional | K88: NUVU - Proyectos - 00 Administrativo - Todos los documentos | L88: Oscar Barragan | M88: Alejandra Gomez | N88: Carlos Sierra | O88: Angel Villasmil | P88: In Progress | Q88: David.Gomez | R88: 55202 | S88: Operations_Team_01
A89: P2017 | B89: P0354 | C89: =F89&" - "&D89&" - "&E89 -> ACA - Agente Cognitivo y Migración - Fixed | D89: Agente Cognitivo y Migración | E89: Fixed | F89: ACA | G89: Implementación | H89: =_xlfn.IFNA(VLOOKUP(F89,clientes!A:B,2,FALSE()),"--") -> Alcaldia de Cali | I89: Inactivo | J89: Alcadia de Cali | K89: Sin Contrato | L89: Kelly Carbonell | M89: Karen Arandia | N89: Nicolas Revollo | O89: Juan Sanchéz | P89: Complete | Q89: N. A. | R89: 57143 - Fixed 57144 - CLOUD | S89: Cloud Operations
A90: P2018 | B90: P0354 | C90: =F90&" - "&D90&" - "&E90 -> ACA - Agente Cognitivo y Migración - Cloud | D90: Agente Cognitivo y Migración | E90: Cloud | F90: ACA | G90: Data | H90: =_xlfn.IFNA(VLOOKUP(F90,clientes!A:B,2,FALSE()),"--") -> Alcaldia de Cali | I90: Inactivo | J90: Alcadia de Cali | K90: Sin Contrato | L90: Kelly Carbonell | M90: Karen Arandia | N90: Nicolas Revollo | O90: Juan Sanchéz | P90: Complete | Q90: N. A. | R90: 57143 - Fixed 57144 - CLOUD | S90: No Aplica
A91: P2009 | B91: P0347 | C91: =F91&" - "&D91&" - "&E91 -> PON - IAPOL-G - IA Generative - Fixed | D91: IAPOL-G - IA Generative | E91: Fixed | F91: PON | G91: Implementación | H91: =_xlfn.IFNA(VLOOKUP(F91,clientes!A:B,2,FALSE()),"--") -> Policia Nacional | I91: Activo | J91: Policia Nacional | K91: OC-152418 5. Documentos contractuales | L91: Daniel Sebastian Vargas | M91: Marcela Sanchéz | N91: Moises Rojas | O91: Camilo Lopez | P91: In Progress | Q91: Victor.Castellanos | R91: 56833 - Fixed 56834 - Ret SW 56835 - Cloud | S91: Juan Goméz | T91: Orden de compra | U91: OC Ponal | V91: CET Ponal | W91: Anexo técnico | Y91: 09.KO | Z91: Comite de Gestión
A92: P2010 | B92: P0347 | C92: =F92&" - "&D92&" - "&E92 -> PON - IAPOL-G - IA Generative - Ret SW | D92: IAPOL-G - IA Generative | E92: Ret SW | F92: PON | G92: Software SW | H92: =_xlfn.IFNA(VLOOKUP(F92,clientes!A:B,2,FALSE()),"--") -> Policia Nacional | I92: Activo | J92: Policia Nacional | K92: OC-152418 5. Documentos contractuales | L92: Daniel Sebastian Vargas | M92: Marcela Sanchéz | N92: Moises Rojas | O92: Camilo Lopez | P92: In Progress | Q92: Victor.Castellanos | R92: 56833 - Fixed 56834 - Ret SW 56835 - Cloud | S92: No Aplica | T92: Orden de compra | U92: OC Ponal | V92: CET Ponal | W92: Anexo técnico | Y92: 09.KO | Z92: Comite de Gestión
A93: P2011 | B93: P0347 | C93: =F93&" - "&D93&" - "&E93 -> PON - IAPOL-G - IA Generative - Cloud | D93: IAPOL-G - IA Generative | E93: Cloud | F93: PON | G93: Data | H93: =_xlfn.IFNA(VLOOKUP(F93,clientes!A:B,2,FALSE()),"--") -> Policia Nacional | I93: Activo | J93: Policia Nacional | K93: OC-152418 5. Documentos contractuales | L93: Daniel Sebastian Vargas | M93: Marcela Sanchéz | N93: Moises Rojas | O93: Camilo Lopez | P93: In Progress | Q93: Victor.Castellanos | R93: 56833 - Fixed 56834 - Ret SW 56835 - Cloud | S93: No Aplica | T93: Orden de compra | U93: OC Ponal | V93: CET Ponal | W93: Anexo técnico | Y93: 09.KO | Z93: Comite de Gestión
A94: P2023 | B94: P0347 | C94: =F94&" - "&D94&" - "&E94 -> PON - IAPOL-G - IA Generative - Ret | D94: IAPOL-G - IA Generative | E94: Ret | F94: PON | G94: Operación | H94: =_xlfn.IFNA(VLOOKUP(F94,clientes!A:B,2,FALSE()),"--") -> Policia Nacional | I94: Activo | J94: Policia Nacional | K94: OC-152418 5. Documentos contractuales | L94: Daniel Sebastian Vargas | M94: Marcela Sanchéz | N94: Moises Rojas | O94: Camilo Lopez | P94: In Progress | Q94: Victor.Castellanos | R94: 56833 - Fixed 56834 - Ret SW 56835 - Cloud | S94: Victor.Castellanos | T94: Orden de compra | U94: OC Ponal | V94: CET Ponal | W94: Anexo técnico | Y94: 09.KO | Z94: Comite de Gestión
A95: P2226 | B95: P0347 | C95: =F95&" - "&D95&" - "&E95 -> PON - IAPOL-G - IA Generative - Other Vendors | D95: IAPOL-G - IA Generative | E95: Other Vendors | F95: PON | G95: Operación | H95: =_xlfn.IFNA(VLOOKUP(F95,clientes!A:B,2,FALSE()),"--") -> Policia Nacional | I95: Activo | J95: Policia Nacional | K95: OC-152418 5. Documentos contractuales | L95: Daniel Sebastian Vargas | M95: Marcela Sanchéz | N95: Moises Rojas | O95: Camilo Lopez | P95: In Progress | Q95: Victor.Castellanos | R95: 56833 - Fixed 56834 - Ret SW 56835 - Cloud | S95: Victor.Castellanos | T95: Orden de compra | U95: OC Ponal | V95: CET Ponal | W95: Anexo técnico | Y95: 09.KO | Z95: Comite de Gestión
A96: P2024 | B96: P0348 | C96: =F96&" - "&D96&" - "&E96 -> CSJ - Digitalización archivo físico - Cloud | D96: Digitalización archivo físico | E96: Cloud | F96: CSJ | G96: Data | H96: =_xlfn.IFNA(VLOOKUP(F96,clientes!A:B,2,FALSE()),"--") -> Consejo Superior de la Judicatura | I96: Inactivo | J96: Consejo Superior de la Judicatura | K96: Pendiente el contrato | L96: David Cortes | M96: Ciliana Capera | N96: Moises Rojas | O96: Gersón Pineda | P96: Complete | Q96: N. A. | R96: 57146 - CLOUD 57147 - Fixed | S96: No Aplica
A97: P2025 | B97: P0348 | C97: =F97&" - "&D97&" - "&E97 -> CSJ - Digitalización archivo físico - Fixed | D97: Digitalización archivo físico | E97: Fixed | F97: CSJ | G97: Implementación | H97: =_xlfn.IFNA(VLOOKUP(F97,clientes!A:B,2,FALSE()),"--") -> Consejo Superior de la Judicatura | I97: Inactivo | J97: Consejo Superior de la Judicatura | K97: Pendiente el contrato | L97: David Cortes | M97: Ciliana Capera | N97: Moises Rojas | O97: Gersón Pineda | P97: Complete | Q97: N. A. | R97: 57146 - CLOUD 57147 - Fixed | S97: Gersón Pineda
A98: P2026 | B98: P0272 | C98: =F98&" - "&D98&" - "&E98 -> CSJ - Migración AWS - Cloud | D98: Migración AWS | E98: Cloud | F98: CSJ | G98: Data | H98: =_xlfn.IFNA(VLOOKUP(F98,clientes!A:B,2,FALSE()),"--") -> Consejo Superior de la Judicatura | I98: Inactivo | J98: Consejo Superior de la Judicatura | K98: OC 122576 | L98: David Cortes | M98: Andres Barrantes | N98: Moises Rojas | O98: Gerson Pineda | P98: Complete | Q98: N. A. | R98: 55136 - Fixed 57148 - CLOUD | S98: No Aplica
A99: P2026 | B99: P0312 | C99: =F99&" - "&D99&" - "&E99 -> BLD - All-Start Program LATAM - Internal | D99: All-Start Program LATAM | E99: Internal | F99: BLD | G99: Interno | H99: =_xlfn.IFNA(VLOOKUP(F99,clientes!A:B,2,FALSE()),"--") -> Blend360 | I99: Activo | J99: N.A. | K99: N.A. | L99: N.A. | M99: N.A. | N99: N.A. | O99: N.A. | P99: In Progress | Q99: N. A. | R99: 5045 | S99: No Aplica
A100: P2027 | B100: P0351 | C100: =F100&" - "&D100&" - "&E100 -> CSJ - PoC Agente para exposición contenido - Cloud | D100: PoC Agente para exposición contenido | E100: Cloud | F100: CSJ | G100: Data | H100: =_xlfn.IFNA(VLOOKUP(F100,clientes!A:B,2,FALSE()),"--") -> Consejo Superior de la Judicatura | I100: Inactivo | J100: Consejo Superior de la Judicatura | K100: Sin contrato | L100: David Cortes | M100: Ciliana Capera | N100: Moises Rojas | O100: Gerson Pineda | P100: Complete | Q100: N. A. | R100: 57149 - CLOUD 57150 - Fixed 57151 - Ret SW | S100: No Aplica
...

Sheet clientes
A1: ClientId | B1: Nombre Cliente | C1: Nombre Corto
A2: ACT | B2: Acttiva | C2: acttiva
A3: AGR | B3: Fiduagraria | C3: fiduagraria
A4: ALC | B4: A la Caja | C4: alacaja
A5: ALI | B5: Alianza | C5: alianza
A6: ALU | B6: AlterU | C6: alteru
A7: AVA | B7: Avanzo | C7: avanzo
A8: BTG | B8: BTG Pactual Colombia | C8: BTG
A9: CCB | B9: Camara de Comercio de Bogotá | C9: ccb
A10: CGR | B10: Contraloría | C10: contraloría
A11: COL | B11: Colcharter | C11: colcharter
A12: COM | B12: Compensar | C12: compensar
... A80: UDS | B80: Universidad de la Sabana | C80: USabana

Sheet Cod.Inactivos
A1: Cod Proyecto | B1: Sigla Cliente | C1: Estado | D1: Nombre Cliente
A2: P0001 | B2: NUV | C2: Inactivo | D2: Nuvu
A3: P0002 | B3: UBO | C3: Inactivo | D3: UBosque
A4: P0003 | B4: SAN | C4: Inactivo | D4: Sanidad
A5: P0004 | B5: SAN | C5: Inactivo | D5: Sanidad
A6: P0005 | B6: UCA | C6: Inactivo | D6: Universidad de Caldas
A7: P0006 | B7: UCA | C7: Inactivo | D7: Universidad de Caldas
A8: P0008 | B8: UCA | C8: Inactivo | D8: Universidad de Caldas
A9: P0009 | B9: UNA | C9: Inactivo | D9: Universidad Nacional de Colombia
A10: P0010 | B10: UNA | C10: Inactivo | D10: Universidad Nacional de Colombia
A11: P0011 | B11: UNA | C11: Inactivo | D11: Universidad Nacional de Colombia
A12: P0012 | B12: UCA | C12: Inactivo | D12: Universidad de Caldas
... A223: P0288 | B223: CJU | C223: Inactivo | D223: Coljuegos

Sheet Codig BLD int
A1: Created Date | B1: HubSpot Deal ID | C1: NetSuite Project ID | D1: Codigo OpenAir Internos | E1: Client | F1: Project | G1: Project Subsidiary | H1: Project owner | I1: Project stage | J1: Allow time entry | K1: Engagement Type | L1: Budget (money) | M1: Start Date | N1: SOW End Date | O1: Expected End Date | P1: Planned | Q1: Worked | R1: Approved | S1: Timesheets approver | T1: % Complete | U1: Active | V1: Portfolio Leader
A2: ######## | C2: 5043 | D2: P0073 | E2: Blend360: DSX Internal | F2: All-Star | G2: Blend360, LLC | H2: Admin, OA | I2: Internal | J2: Yes | K2: Other | L2: 0.00 USD | M2: ######## | P2: 0 | Q2: 36616.22 | R2: 36608.22 | S2: [Self approver] | T2: 0 | U2: Yes | V2: PORTFOLIO LEADER, OTHER [Inactive]
A3: ######## | C3: 5044 | D3: P0074 | E3: Blend360: DSX Internal | F3: B360 Materials Development | G3: Blend360, LLC | H3: Admin, OA | I3: Internal | J3: Yes | K3: Other | L3: 0.00 USD | M3: ######## | P3: 0 | Q3: 15668.02 | R3: 15597.52 | S3: [Self approver] | T3: 0 | U3: Yes | V3: PORTFOLIO LEADER, OTHER [Inactive]
A4: ######## | C4: 5045 | D4: P0075 | E4: Blend360: DSX Internal | F4: Business Development - New Logo | G4: Blend360, LLC | H4: Admin, OA | I4: Internal | J4: Yes | K4: Other | L4: 0.00 USD | M4: ######## | P4: 1035.16 | Q4: 56751.6 | R4: 56578.1 | S4: [Self approver] | T4: 100 | U4: Yes | V4: PORTFOLIO LEADER, OTHER [Inactive]
A5: ######## | C5: 5046 | D5: P0076 | E5: Blend360: DSX Internal | F5: Business Systems Development & Support | G5: Blend360, LLC | H5: Admin, OA | I5: Internal | J5: Yes | K5: Other | L5: 0.00 USD | M5: ######## | P5: 0 | Q5: 3647.4 | R5: 3647.4 | S5: [Self approver] | T5: 0 | U5: Yes | V5: PORTFOLIO LEADER, OTHER [Inactive]
A6: ######## | C6: 5047 | D6: P0077 | E6: Blend360: DSX Internal | F6: COE - Center of Excellence (CLOSED) | G6: Blend360, LLC | H6: Admin, OA | I6: Internal | J6: No | K6: Other | L6: 0.00 USD | M6: ######## | P6: 0 | Q6: 0 | R6: 0 | S6: [Self approver] | T6: 0 | U6: No | V6: PORTFOLIO LEADER, OTHER [Inactive]
A7: ######## | C7: 5048 | D7: P0078 | E7: Blend360: DSX Internal | F7: Cloud Platform Upkeep/Enhancement | G7: Blend360, LLC | H7: Admin, OA | I7: Internal | J7: No | K7: Other | L7: 0.00 USD | M7: ######## | N7: ######## | P7: 0 | Q7: 430 | R7: 430 | S7: [Self approver] | T7: 0 | V7: PORTFOLIO LEADER, OTHER [Inactive]
A8: ######## | B8: Non-Funded 03 | C8: 5049 | D8: P0079 | E8: Blend360: DSX Internal | F8: COE - Advanced ML Algo Adaption | G8: Blend360, LLC | H8: JIA, FENG | I8: Internal | J8: Yes | K8: Other | L8: 0.00 USD | M8: ######## | P8: 0 | Q8: 412.2 | R8: 412.2 | S8: [Self approver] | T8: 0 | U8: Yes | V8: PORTFOLIO LEADER, OTHER [Inactive]
A9: ######## | B9: Non-Funded 04 | C9: 5050 | D9: P0080 | E9: Blend360: DSX Internal | F9: COE - BI Product management | G9: Blend360, LLC | H9: RAGHAVAN, SRINIVAS | I9: Internal | J9: Yes | K9: Other | L9: 0.00 USD | M9: ######## | P9: 0 | Q9: 7350 | R9: 7350 | S9: [Self approver] | T9: 0 | U9: Yes | V9: PORTFOLIO LEADER, OTHER [Inactive]
A10: ######## | B10: Non-Funded 05 | C10: 5051 | D10: P0081 | E10: Blend360: DSX Internal | F10: COE - ML Deployment and Ops | G10: Blend360, LLC | H10: JIA, FENG | I10: Internal | J10: Yes | K10: Other | L10: 0.00 USD | M10: ######## | P10: 0 | Q10: 1014.9 | R10: 1014.9 | S10: [Self approver] | T10: 0 | U10: Yes | V10: PORTFOLIO LEADER, OTHER [Inactive]
A11: ######## | B11: Non-Funded 06 | C11: 5052 | D11: P0082 | E11: Blend360: DSX Internal | F11: COE - Optimization and prescriptive analytics | G11: Blend360, LLC | H11: JIA, FENG | I11: Internal | J11: Yes | K11: Other | L11: 0.00 USD | M11: ######## | P11: 0 | Q11: 1326.5 | R11: 1326.5 | S11: [Self approver] | T11: 0 | U11: Yes | V11: PORTFOLIO LEADER, OTHER [Inactive]
A12: ######## | C12: 5053 | D12: P0083 | E12: Blend360: DSX Internal | F12: COE - Center of Excellence | G12: Blend360, LLC | H12: Admin, OA | I12: Internal | J12: Yes | K12: Other | L12: 0.00 USD | M12: ######## | P12: 1684.96 | Q12: 28825.72 | R12: 28689.72 | S12: [Self approver] | T12: 0 | U12: Yes | V12: PORTFOLIO LEADER, OTHER [Inactive]
A13: ######## | B13: Non-Funded 07 | C13: 5054 | D13: P0084 | E13: Blend360: DSX Internal | F13: Data Practice Ops | G13: Blend360, LLC | H13: BERRY, ZACHARY | I13: Internal | J13: Yes | K13: Other | L13: 0.00 USD | M13: ######## | P13: 192 | Q13: 4279.25 | R13: 4279.25 | S13: [Self approver] | T13: 0 | U13: Yes | V13: PORTFOLIO LEADER, OTHER [Inactive]
A14: ######## | B14: Non-Funded 08 | C14: 5055 | D14: P0085 | E14: Blend360: DSX Internal | F14: Data Practice Support | G14: Blend360, LLC | H14: BERRY, ZACHARY | I14: Internal | J14: Yes | K14: Other | L14: 0.00 USD | M14: ######## | P14: 3598.37 | Q14: 7491.25 | R14: 7471.75 | S14: [Self approver] | T14: 0 | U14: Yes | V14: PORTFOLIO LEADER, OTHER [Inactive]
A15: ######## | C15: 5056 | D15: P0086 | E15: Blend360: DSX Internal | F15: Events | G15: Blend360, LLC | H15: Admin, OA | I15: Internal | J15: Yes | K15: Other | L15: 0.00 USD | M15: ######## | P15: 0 | Q15: 5475.45 | R15: 5462.45 | S15: [Self approver] | T15: 0 | U15: Yes | V15: PORTFOLIO LEADER, OTHER [Inactive]
A16: ######## | C16: 5057 | D16: P0087 | E16: Blend360: DSX Internal | F16: Internal Development | G16: Blend360, LLC | H16: Admin, OA | I16: Internal | J16: No | K16: Other | L16: 0.00 USD | M16: ######## | P16: 0 | Q16: 17579.6 | R16: 17579.6 | S16: [Self approver] | T16: 0 | U16: No | V16: PORTFOLIO LEADER, OTHER [Inactive]
A17: ######## | C17: 5058 | D17: P0088 | E17: Blend360: DSX Internal | F17: Marketing | G17: Blend360, LLC | H17: Admin, OA | I17: Internal | J17: Yes | K17: Other | L17: 0.00 USD | M17: ######## | P17: 0 | Q17: 5696.95 | R17: 5573.95 | S17: [Self approver] | T17: 0 | U17: Yes | V17: PORTFOLIO LEADER, OTHER [Inactive]
A18: ######## | C18: 5059 | D18: P0089 | E18: Blend360: DSX Internal | F18: Meetings (Non-Client) | G18: Blend360, LLC | H18: Admin, OA | I18: Internal | J18: Yes | K18: Other | L18: 0.00 USD | M18: ######## | P18: 24 | Q18: ######## | R18: ######## | S18: [Self approver] | T18: 0 | U18: Yes | V18: PORTFOLIO LEADER, OTHER [Inactive]
A19: ######## | C19: 5060 | D19: P0090 | E19: Blend360: DSX Internal | F19: Non-Client Work | G19: Blend360, LLC | H19: Admin, OA | I19: Internal | J19: No | K19: Other | L19: 0.00 USD | M19: ######## | P19: 0 | Q19: 5830.5 | R19: 5830.5 | S19: [Self approver] | T19: 0 | U19: No | V19: PORTFOLIO LEADER, OTHER [Inactive]
A20: ######## | C20: 5061 | D20: P0091 | E20: Blend360: DSX Internal | F20: Performance Reviews | G20: Blend360, LLC | H20: Admin, OA | I20: Internal | J20: Yes | K20: Other | L20: 0.00 USD | M20: ######## | P20: 2 | Q20: 1576.75 | R20: 1539.25 | S20: [Self approver] | T20: 0 | U20: Yes | V20: PORTFOLIO LEADER, OTHER [Inactive]
A21: ######## | C21: 5062 | D21: P0092 | E21: Blend360: DSX Internal | F21: Platform Support & Enhancement | G21: Blend360, LLC | H21: Admin, OA | I21: Internal | J21: Yes | K21: Other | L21: 0.00 USD | M21: ######## | P21: 10 | Q21: 929 | R21: 929 | S21: [Self approver] | T21: 0 | U21: Yes | V21: PORTFOLIO LEADER, OTHER [Inactive]
A22: ######## | C22: 5063 | D22: P0093 | E22: Blend360: DSX Internal | F22: Recruiting | G22: Blend360, LLC | H22: Admin, OA | I22: Internal | J22: Yes | K22: Other | L22: 0.00 USD | M22: ######## | P22: 0 | Q22: 15674.05 | R22: 15659.05 | S22: [Self approver] | T22: 0 | U22: Yes | V22: PORTFOLIO LEADER, OTHER [Inactive]
A23: ######## | C23: 5064 | D23: P0094 | E23: Blend360: DSX Internal | F23: Time Off | G23: Blend360, LLC | H23: Admin, OA | I23: Internal | J23: Yes | K23: Other | L23: 0.00 USD | M23: ######## | P23: 6444 | Q23: ######## | R23: ######## | S23: [Self approver] | T23: 100 | U23: Yes | V23: PORTFOLIO LEADER, OTHER [Inactive]
A24: ######## | C24: 5065 | D24: P0095 | E24: Blend360: DSX Internal | F24: Training / Career Development | G24: Blend360, LLC | H24: Admin, OA | I24: Internal | J24: Yes | K24: Other | L24: 0.00 USD | M24: ######## | P24: 422.4 | Q24: ######## | R24: ######## | S24: [Self approver] | T24: 0 | U24: Yes | V24: PORTFOLIO LEADER, OTHER [Inactive]
A25: ######## | C25: 5066 | D25: P0096 | E25: Blend360: DSX Internal | F25: Travel | G25: Blend360, LLC | H25: Admin, OA | I25: Internal | J25: Yes | K25: Other | L25: 0.00 USD | M25: ######## | P25: 0 | Q25: 4513.6 | R25: 4511.6 | S25: [Self approver] | T25: 0 | U25: Yes | V25: PORTFOLIO LEADER, OTHER [Inactive]
A26: ######## | B26: 12345 - TEST - DELETE ME | C26: 5067 | D26: P0097 | E26: Blend360: DSX Internal | F26: Volunteer Work | G26: Blend360, LLC | H26: Admin, OA | I26: Internal | J26: Yes | K26: Other | L26: 0.00 USD | M26: ######## | P26: 0 | Q26: 526 | R26: 526 | S26: [Self approver] | T26: 0 | U26: Yes | V26: PORTFOLIO LEADER, OTHER [Inactive]
A27: ######## | C27: 5068 | D27: P0098 | E27: Blend360: DSX Internal | F27: Data Development | G27: Blend360, LLC | H27: BERRY, ZACHARY | I27: Internal | J27: No | K27: Other | L27: 0.00 USD | M27: ######## | P27: 0 | Q27: 2579.75 | R27: 2579.75 | S27: [Self approver] | T27: 0 | V27: PORTFOLIO LEADER, OTHER [Inactive]
A28: ######## | C28: 5069 | D28: P0099 | E28: Blend360: DSX Internal | F28: NetSuite ERP/OpenAir Implementation | G28: Blend360, LLC | H28: LI, CJ | I28: Internal | J28: No | K28: Other | L28: 0.00 USD | M28: ######## | P28: 18 | Q28: 1607.5 | R28: 1578 | S28: [Self approver] | T28: 0 | V28: PORTFOLIO LEADER, OTHER [Inactive]
A29: ######## | B29: Non-Funded 11 | C29: 5986 | D29: P0314 | E29: Blend360: DSX Internal | F29: Measurement Library | G29: Blend360, LLC | H29: NUERNBERGER, SCOTT | I29: Internal | J29: Yes | K29: Other | L29: 0.00 USD | M29: ######## | P29: 65.04 | Q29: 1869.5 | R29: 1869.5 | S29: [Self approver] | T29: 0 | U29: Yes | V29: PORTFOLIO LEADER, OTHER [Inactive]
A30: ######## | C30: 6102 | D30: P0321 | E30: Blend360: DSX Internal | G30: Blend360, LLC | H30: Admin, OA | I30: Internal | J30: Yes | K30: Other | L30: 0.00 USD | M30: ######## | P30: 3339.12 | Q30: 78793.07 | R30: 78542.57 | T30: 0 | U30: Yes | V30: PORTFOLIO LEADER, OTHER [Inactive]
A31: ######## | C31: 7830 | D31: P0400 | E31: Blend360: DSX Internal | F31: Blend Academy Taskforce | G31: Blend360, LLC | H31: ROBERTS, SARA | I31: Internal | J31: No | K31: Other | L31: 0.00 USD | M31: ######## | P31: 0 | Q31: 36.25 | R31: 36.25 | S31: [Self approver] | T31: 0 | V31: PORTFOLIO LEADER, OTHER [Inactive]
A32: ######## | B32: Non-Funded 01 | C32: 10757 | D32: P0464 | E32: Blend360: DSX Internal | F32: All-Star Program Capability Leadership | G32: Blend360, LLC | H32: LI, CJ | I32: Internal | J32: Yes | K32: Other | L32: 0.00 USD | M32: 44927 | P32: 1591.92 | Q32: 1126 | R32: 1126 | S32: [Self approver] | T32: 0 | U32: Yes | V32: PORTFOLIO LEADER, OTHER [Inactive]
A33: ######## | C33: 11228 | D33: 4P085 | E33: Blend360: DSX Internal | F33: Promotions & Innovations | G33: Blend360, LLC | H33: COURBOIS, PIP | I33: Internal | J33: No | K33: Other | L33: 0.00 USD | M33: 44927 | P33: 154.08 | Q33: 54 | R33: 54 | S33: [Self approver] | T33: 0 | V33: PORTFOLIO LEADER, OTHER [Inactive]
A34: ######## | B34: Non-Funded 09 | C34: 11243 | D34: P0496 | E34: Blend360: DSX Internal | F34: Data Science Offerings 2023 | G34: Blend360, LLC | H34: NUERNBERGER, SCOTT | I34: Internal | J34: No | K34: Other | L34: 0.00 USD | M34: 44927 | N34: ######## | P34: 203.6 | Q34: 567.9 | R34: 567.9 | S34: [Self approver] | T34: 46 | V34: PORTFOLIO LEADER, OTHER [Inactive]
A35: ######## | B35: Non-Funded 12 | C35: 14993 | D35: P0586 | E35: Blend360: DSX Internal | F35: Tech Go Big | G35: Blend360, LLC | H35: FULLER, ROB | I35: Internal | J35: No | K35: Other | L35: 0.00 USD | M35: 44986 | P35: 0 | Q35: 160.5 | R35: 160.5 | S35: [Self approver] | T35: 0 | V35: PORTFOLIO LEADER, OTHER [Inactive]
A36: 45022 | B36: Non-Funded 02 | C36: 15318 | D36: P0601 | E36: Blend360: DSX Internal | F36: AME Measurement Accelerator | G36: Blend360, LLC | H36: FORAN, JOE | I36: Internal | J36: Yes | K36: Other | L36: 0.00 USD | M36: 45019 | P36: 1989.2 | Q36: 1191.5 | R36: 1191.5 | S36: [Self approver] | T36: 77 | U36: Yes | V36: PORTFOLIO LEADER, OTHER [Inactive]
A37: ######## | C37: 16257 | D37: P0617 | E37: Blend360: DSX Internal | F37: Blend360 Intranet Project | G37: Blend360, LLC | H37: PORTFOLIO LEADER, OTHER | I37: Internal | J37: No | K37: Other | L37: 0.00 USD | M37: ######## | N37: ######## | P37: 0 | Q37: 240 | R37: 240 | S37: [Self approver] | T37: 0 | V37: PORTFOLIO LEADER, OTHER [Inactive]
A38: ######## | C38: 16676 | D38: P0628 | E38: Blend360: DSX Internal | F38: US DSX HubSpot Implementation | G38: Blend360, LLC | H38: BISKUP, TIM | I38: Internal | J38: No | K38: Other | L38: 0.00 USD | M38: ######## | N38: ######## | P38: 1050.4 | Q38: 697 | R38: 697 | S38: [Self approver] | T38: 0 | V38: PORTFOLIO LEADER, OTHER [Inactive]
A39: ######## | C39: 16997 | D39: P0636 | E39: Blend360: DSX Internal | F39: Accelerator – BlendGPT | G39: Blend360, LLC | H39: CHIPMAN, BO | I39: Internal | J39: No | K39: Other | L39: 0.00 USD | M39: 45047 | N39: ######## | P39: 436 | Q39: 1368.5 | R39: 1368.5 | S39: [Self approver] | T39: 0 | V39: PORTFOLIO LEADER, OTHER [Inactive]
A40: 45051 | B40: Non-Funded 10 | C40: 17223 | D40: P0649 | E40: Blend360: DSX Internal | F40: DSX Management Dashboard | G40: Blend360, LLC | H40: CHEN, PETE | I40: Internal | J40: Yes | K40: Other | L40: 0.00 USD | M40: ######## | P40: 12398.96 | Q40: 10029.4 | R40: 10029.4 | S40: [Self approver] | T40: 0 | U40: Yes | V40: PORTFOLIO LEADER, OTHER [Inactive]
A41: ######## | C41: 17474 | D41: P0676 | E41: Blend360: DSX Internal | F41: DSX US Smartrecruiter Reporting Conversion | G41: Blend360, LLC | H41: CHEN, PETE | I41: Internal | J41: No | K41: Other | L41: 0.00 USD | M41: ######## | N41: ######## | P41: 0 | Q41: 416 | R41: 416 | S41: [Self approver] | T41: 0 | V41: PORTFOLIO LEADER, OTHER [Inactive]
P42: 50559.61 | Q42: ######## | R42: ########
L43: 0.00 EUR
L44: 0.00 USD
L45: 0.00 UYU

Sheet Parameter
A1: Estado | E1: Equipo de Soporte
A2: Activo | E2: Sin Asignar
A3: Inactivo | E3: N. A.
E4: Ronald.Porras
E5: Cristian.Angel
E6: Miguel.Carrillo
E7: Carlos.Aroca
E8: David.Gomez
E9: Fernando.Garcia
E10: Valentina.Salazar
E11: Victor.Castellanos

Sheet Sheet2
A1: Sigla | B1: (Multiple Items)
A2: Status | B2: Activo
A4: Client Name | B4: Project Manager
A5: Banco Interamericano de Desarrollo
A6: Banco Interamericano de Desarrollo | B6: Diana Castro
A8: Cámara de Comercio de Cali
A9: Cámara de Comercio de Cali | B9: Kelly Carbonell
A11: Coljuegos
A12: Coljuegos | B12: Juan Bernal
A14: Consejo Superior de la Judicatura
A15: Consejo Superior de la Judicatura | B15: David Cortes
A17: DIAN
A18: DIAN | B18: Juan Bernal
A20: Empresa De Transporte Masivo Del Valle De Aburrá Limitada
A21: Empresa De Transporte Masivo Del Valle De Aburrá Limitada | B21: Diana Rojas
A23: Financiera de Desarrollo Nacional
A24: Financiera de Desarrollo Nacional | B24: David Cortes
A26: Fondo Adaptación
A27: Fondo Adaptación | B27: Daniel Sebastian Vargas
A29: JPMP - Justicia Penal Militar y Policial
A30: JPMP - Justicia Penal Militar y Policial | B30: David Cortes
A32: Policia Nacional
A33: Policia Nacional | B33: Daniel Sebastian Vargas
A35: Progresión
A36: Progresión | B36: Oscar Barragan
A38: Sanidad
A39: Sanidad | B39: Diana Castro
A41: Secretaria Distrital del Hábitat
A42: Secretaria Distrital del Hábitat | B42: David Cortes
A44: UBosque
A45: UBosque | B45: David Cortes
A47: Unidad Administrativa Especial de Catastro Distrital
A48: Unidad Administrativa Especial de Catastro Distrital | B48: Oscar Barragan
A50: Universidad de Caldas
A51: Universidad de Caldas | B51: Oscar Barragan
A53: Universidad Nacional de Colombia
A54: Universidad Nacional de Colombia | B54: Oscar Barragan
A56: Instituto Colombiano Para La Evaluacion De La Educacion ICFES
A57: Instituto Colombiano Para La Evaluacion De La Educacion ICFES | B57: Juan Bernal
A59: Superintendencia Servicios Públicos Domiciliarios
A60: Superintendencia Servicios Públicos Domiciliarios | B60: Miguel Garcia
A62: BTG Pactual
A63: BTG Pactual | B63: Oscar Barragan
A65: Colpensiones
A66: Colpensiones | B66: N.A.
A68: BTG Pactual Colombia
A69: BTG Pactual Colombia | B69: Oscar Barragan
A71: Grand Total

Sheet Prueba
A1: Project ID | B1: ID Old | C1: Project Name Full | D1: Objetivo | E1: Blend Project Type | F1: Sigla | G1: Type Project | H1: Client Name | I1: Status | J1: Folder Legal | K1: Foldel Project Admin | L1: Project Manager | M1: Account Manager | N1: Technical Leader | O1: Sr Tech | P1: Contract Type | Q1: Support Engineer | R1: NetSuite | S1: Team | T1: Tipo de contrato | U1: Contrato | V1: CET | W1: Ficha tecnica | X1: Legal | Y1: Columna1
A2: P0083 | B2: P0105 | C2: COE – Center of Excellence (Reuniones internas / Entrega interna de proyectos dedicado) | D2: COE - Center of Excellence | E2: Internal | F2: BLD | G2: Interno | H2: =_xlfn.IFNA(VLOOKUP(F2,clientes!A:B,2,FALSE()),"--") -> Blend360 | I2: Activo | J2: N.A. | K2: N.A. | L2: N.A. | M2: N.A. | N2: N.A. | O2: N.A. | P2: In Progress | Q2: N. A. | R2: 5045 | S2: No Aplica
A3: P0089 | B3: P0221 | C3: =F3&" - "&D3&" - "&E3 -> BLD - Meetings & Training - Internal | D3: Meetings & Training | E3: Internal | F3: BLD | G3: Interno | H3: =_xlfn.IFNA(VLOOKUP(F3,clientes!A:B,2,FALSE()),"--") -> Blend360 | I3: Activo | J3: N.A. | K3: N.A. | L3: N.A. | M3: N.A. | N3: N.A. | O3: N.A. | P3: In Progress | Q3: N. A. | R3: 5045 | S3: No Aplica
A4: P0094 | B4: P0312 | C4: =F4&" - "&D4&" - "&E4 -> BLD - Time Off & Holiday - Internal | D4: Time Off & Holiday | E4: Internal | F4: BLD | G4: Interno | H4: =_xlfn.IFNA(VLOOKUP(F4,clientes!A:B,2,FALSE()),"--") -> Blend360 | I4: Activo | J4: N.A. | K4: N.A. | L4: N.A. | M4: N.A. | N4: N.A. | O4: N.A. | P4: In Progress | Q4: N. A. | R4: 5045 | S4: No Aplica
A5: P1920 | B5: P0070 | C5: =F5&" - "&D5&" - "&E5 -> BTG - SmartCash - Operación - Ret SW | D5: SmartCash - Operación | E5: Ret SW | F5: BTG | G5: Software SW | H5: =_xlfn.IFNA(VLOOKUP(F5,clientes!A:B,2,FALSE()),"--") -> BTG Pactual Colombia | I5: Activo | J5: BTG Pactual S.A | K5: Cto Mantenimiento y soporte CP Suite | L5: Oscar Barragan | M5: Daniela Muñoz | N5: Carlos Sierra | O5: Ariane Hernandez | P5: In Progress | Q5: Miguel.Carrillo | R5: 55132 - Ret SW 56836 - Ret | S5: No Aplica
A6: P2012 | B6: P0070 | C6: =F6&" - "&D6&" - "&E6 -> BTG - SmartCash - Operación - Ret | D6: SmartCash - Operación | E6: Ret | F6: BTG | G6: Operación | H6: BTG Pactual | I6: Activo | J6: BTG Pactual S.A | K6: BTG COLOMBIA 13.580 | L6: Oscar Barragan | M6: Daniela Muñoz | N6: Carlos Sierra | O6: Ariane Hernandez | P6: In Progress | Q6: Miguel.Carrillo | R6: 55132 - Ret SW 56836 - Ret | S6: Operations_Team_01
A7: P1903 | B7: P0337 | C7: =F7&" - "&D7&" - "&E7 -> ACA - Catastro Cali Piloto Dashboard - Cloud | D7: Catastro Cali Piloto Dashboard | E7: Cloud | F7: ACA | G7: Data | H7: =_xlfn.IFNA(VLOOKUP(F7,clientes!A:B,2,FALSE()),"--") -> Alcaldia de Cali | I7: Inactivo | J7: Alcadia de Cali | K7: N.A. | L7: Kelly Carbonell | M7: Karen Arandia | N7: Carlos Sierra | O7: Simón Lopez | P7: Complete | Q7: N. A. | R7: 55115 - CLOUD 55116 - Fixed | S7: No Aplica | U7: Contrato UBO - Operación Cloud - Cloud
A8: P1904 | B8: P0337 | C8: =F8&" - "&D8&" - "&E8 -> ACA - Catastro Cali Piloto Dashboard - Fixed | D8: Catastro Cali Piloto Dashboard | E8: Fixed | F8: ACA | G8: Implementación | H8: =_xlfn.IFNA(VLOOKUP(F8,clientes!A:B,2,FALSE()),"--") -> Alcaldia de Cali | I8: Inactivo | J8: Alcadia de Cali | K8: N.A. | L8: Kelly Carbonell | M8: Karen Arandia | N8: Carlos Sierra | O8: Simón Lopez | P8: Complete | Q8: N. A. | R8: 55115 - CLOUD 55116 - Fixed | S8: Simón Lopez | U8: Contrato DIA - Aprovisionamiento multinube - Lote 3 - Cloud
A9: P1905 | B9: P0323 | C9: =F9&" - "&D9&" - "&E9 -> ACA - Fase 1 Datacali - Fixed | D9: Fase 1 Datacali | E9: Fixed | F9: ACA | G9: Implementación | H9: =_xlfn.IFNA(VLOOKUP(F9,clientes!A:B,2,FALSE()),"--") -> Alcaldia de Cali | I9: Inactivo | J9: Alcadia de Cali | K9: Contrato No. 4134.010.26.1.0441-2024 | L9: Kelly Carbonell | M9: Karen Arandia | N9: Carlos Sierra | O9: Simón Lopez | P9: Complete | Q9: N. A. | R9: 55117 - Fixed 55118 - Ret SW 55119 - CLOUD | S9: Simón Lopez | U9: Contrato JPM - Cloud Managed Services 2023-25 - Ret
A10: P1906 | B10: P0323 | C10: =F10&" - "&D10&" - "&E10 -> ACA - Fase 1 Datacali - Ret SW | D10: Fase 1 Datacali | E10: Ret SW | F10: ACA | G10: Software SW | H10: =_xlfn.IFNA(VLOOKUP(F10,clientes!A:B,2,FALSE()),"--") -> Alcaldia de Cali | I10: Inactivo | J10: Alcadia de Cali | K10: Contrato No. 4134.010.26.1.0441-2024 | L10: Kelly Carbonell | M10: Karen Arandia | N10: Carlos Sierra | O10: Simón Lopez | P10: Complete | Q10: N. A. | R10: 55117 - Fixed 55118 - Ret SW 55119 - CLOUD | S10: No Aplica | U10: Contrato JPM - Cloud Managed Services 2023-25 - Cloud
A11: P1907 | B11: P0323 | C11: =F11&" - "&D11&" - "&E11 -> ACA - Fase 1 Datacali - Cloud | D11: Fase 1 Datacali | E11: Cloud | F11: ACA | G11: Data | H11: =_xlfn.IFNA(VLOOKUP(F11,clientes!A:B,2,FALSE()),"--") -> Alcaldia de Cali | I11: Inactivo | J11: Alcadia de Cali | K11: Contrato No. 4134.010.26.1.0441-2024 | L11: Kelly Carbonell | M11: Karen Arandia | N11: Carlos Sierra | O11: Simón Lopez | P11: Complete | Q11: N. A. | R11: 55117 - Fixed 55118 - Ret SW 55119 - CLOUD | S11: No Aplica | U11: #N/A
A12: P1908 | B12: P0255 | C12: =F12&" - "&D12&" - "&E12 -> AGA - Datalake Grupo de Energía de Bogotá - Cloud | D12: Datalake Grupo de Energía de Bogotá | E12: Cloud | F12: AGA | G12: Data | H12: =_xlfn.IFNA(VLOOKUP(F12,clientes!A:B,2,FALSE()),"--") -> Agata Data | I12: Inactivo | J12: Agata GEB- SDP | K12: Otrosi n° 3 Anexo 2 | L12: Kelly Carbonell | M12: Alejandra Gomez | N12: Carlos Sierra | O12: Jose Gallego | P12: Complete | Q12: N. A. | R12: 55120 - CLOUD 55121 - Ret SW 55122 - Ret | S12: No Aplica | U12: Contrato CCC - IaaS para DRP - Cloud
A13: P1909 | B13: P0255 | C13: =F13&" - "&D13&" - "&E13 -> AGA - Datalake Grupo de Energía de Bogotá - Ret SW | D13: Datalake Grupo de Energía de Bogotá | E13: Ret SW | F13: AGA | G13: Software SW | H13: =_xlfn.IFNA(VLOOKUP(F13,clientes!A:B,2,FALSE()),"--") -> Agata Data | I13: Inactivo | J13: Agata GEB- SDP | K13: Otrosi n° 3 Anexo 2 | L13: Kelly Carbonell | M13: Alejandra Gomez | N13: Carlos Sierra | O13: Jose Gallego | P13: Complete | Q13: N. A. | R13: 55120 - CLOUD 55121 - Ret SW 55122 - Ret | S13: No Aplica | U13: #N/A
A14: P1910 | B14: P0255 | C14: =F14&" - "&D14&" - "&E14 -> AGA - Datalake Grupo de Energía de Bogotá - Ret | D14: Datalake Grupo de Energía de Bogotá | E14: Ret | F14: AGA | G14: Operación | H14: =_xlfn.IFNA(VLOOKUP(F14,clientes!A:B,2,FALSE()),"--") -> Agata Data | I14: Inactivo | J14: Agata GEB- SDP | K14: Anexo 2 GEB- SDP | L14: Kelly Carbonell | M14: Alejandra Gomez | N14: Carlos Sierra | O14: Jose Gallego | P14: Complete | Q14: N. A. | R14: 55120 - CLOUD 55121 - Ret SW 55122 - Ret | S14: Operations_Team_01 | U14: Contrato UNA - Regalías Sikie - Cloud
A15: P1910 | B15: P0278 | C15: =F15&" - "&D15&" - "&E15 -> AGR - Multicash Operación - Pending | D15: Multicash Operación | E15: Pending | F15: AGR | G15: Operación | H15: =_xlfn.IFNA(VLOOKUP(F15,clientes!A:B,2,FALSE()),"--") -> Fiduagraria | I15: Inactivo | J15: Fiduagraria - Multicash | K15: Otrosí No 2 Contrato 040 de 2021 | L15: Kelly Carbonell | M15: Alejandra Gomez | N15: Carlos Sierra | O15: Angel Villasmil | P15: Complete | Q15: Miguel.Carrillo | S15: Operations_Team_01 | U15: Contrato UNA - Regalías Sikie - Ret
A16: P1911 | B16: P0321 | C16: =F16&" - "&D16&" - "&E16 -> AGR - CP Suite ( Smartcash) Operación - Ret | D16: CP Suite ( Smartcash) Operación | E16: Ret | F16: AGR | G16: Operación | H16: =_xlfn.IFNA(VLOOKUP(F16,clientes!A:B,2,FALSE()),"--") -> Fiduagraria | I16: Inactivo | J16: Fiduagraria- CP Suite | K16: OTROSI 3 CTO 032-2021. HIGH TECH | L16: Kelly Carbonell | M16: Alejandra Gomez | N16: Carlos Sierra | O16: Angel Villasmil | P16: Complete | Q16: Miguel.Carrillo | R16: 55123 | S16: Operations_Team_01 | U16: Contrato UNA - Regalías Sikie - Ret
A17: P1912 | B17: P0339 | C17: =F17&" - "&D17&" - "&E17 -> AGR - Quicksight Operación 2025 - Cloud | D17: Quicksight Operación 2025 | E17: Cloud | F17: AGR | G17: Data | H17: =_xlfn.IFNA(VLOOKUP(F17,clientes!A:B,2,FALSE()),"--") -> Fiduagraria | I17: Inactivo | J17: Fiduagraria - Quicksight | K17: OTROSI 3 CTO 037-2021. HIGH TECH. | L17: Kelly Carbonell | M17: Alejandra Gomez | N17: Carlos Sierra | O17: Angel Villasmil | P17: Complete | Q17: N. A. | R17: 55124 | S17: No Aplica | U17: Contrato UNA - Fortinet - Fixed
A18: P1913 | B18: P0338 | C18: =F18&" - "&D18&" - "&E18 -> AGR - Snaptask Operación 2025 - Ret | D18: Snaptask Operación 2025 | E18: Ret | F18: AGR | G18: Operación | H18: =_xlfn.IFNA(VLOOKUP(F18,clientes!A:B,2,FALSE()),"--") -> Fiduagraria | I18: Inactivo | J18: Fiduagraria - Snaptask | K18: OTROSI 3 CTO 038-2021. HIGH TECH | L18: Kelly Carbonell | M18: Alejandra Gomez | N18: Carlos Sierra | O18: Angel Villasmil | P18: Complete | Q18: Miguel.Carrillo | R18: 55124 | S18: Operations_Team_01 | U18: Contrato UNA - Fortinet - Cloud
A19: P1968 | B19: P0168 | C19: =F19&" - "&D19&" - "&E19 -> UBO - Operación Cloud - Cloud | D19: Operación Cloud | E19: Cloud | F19: UBO | G19: Data | H19: =_xlfn.IFNA(VLOOKUP(F19,clientes!A:B,2,FALSE()),"--") -> UBosque | I19: Activo | J19: Universidad del Bosque | K19: Cto PS 250-2021 | L19: David Cortes | M19: Alejandra Gomez | N19: Samuel Escobar | O19: N.A. | P19: In Progress | Q19: N. A. | R19: 55180 | S19: No Aplica
A20: P1932 | B20: P0217 | C20: =F20&" - "&D20&" - "&E20 -> DIA - Aprovisionamiento multinube - Lote 3 - Cloud | D20: Aprovisionamiento multinube - Lote 3 | E20: Cloud | F20: DIA | G20: Data | H20: =_xlfn.IFNA(VLOOKUP(F20,clientes!A:B,2,FALSE()),"--") -> DIAN | I20: Activo | J20: Dian | K20: Convenio Contractual 92872-031-2022 | L20: Juan Bernal | M20: Ciliana Capera | N20: Nicolas Revollo | O20: Juan Sanchéz | P20: In Progress | Q20: N. A. | R20: 55144 | S20: Cloud Operations
A21: P1947 | B21: P0265 | C21: =F21&" - "&D21&" - "&E21 -> JPM - Cloud Managed Services 2023-25 - Ret | D21: Cloud Managed Services 2023-25 | E21: Ret | F21: JPM | G21: Operación | H21: =_xlfn.IFNA(VLOOKUP(F21,clientes!A:B,2,FALSE()),"--") -> JPMP - Justicia Penal Militar y Policial | I21: Activo | J21: Justicia Penal Militar | K21: OC 119973 | L21: Juan Bernal | M21: Marcela Sanchéz | N21: Nicolas Revollo | O21: Juan Sanchéz | P21: In Progress | Q21: N. A. | R21: 55159 - Ret 55160 - CLOUD | S21: Cloud Operations
A22: P1948 | B22: P0265 | C22: =F22&" - "&D22&" - "&E22 -> JPM - Cloud Managed Services 2023-25 - Cloud | D22: Cloud Managed Services 2023-25 | E22: Cloud | F22: JPM | G22: Data | H22: =_xlfn.IFNA(VLOOKUP(F22,clientes!A:B,2,FALSE()),"--") -> JPMP - Justicia Penal Militar y Policial | I22: Activo | J22: Justicia Penal Militar | K22: OC 119973 | L22: Juan Bernal | M22: Marcela Sanchéz | N22: Nicolas Revollo | O22: Juan Sanchéz | P22: In Progress | Q22: N. A. | R22: 55159 - Ret 55160 - CLOUD | S22: Cloud Operations
A23: P1918 | B23: P0302 | C23: =F23&" - "&D23&" - "&E23 -> BID - Migración y Diseño de Arquitectura AWS - Cloud | D23: Migración y Diseño de Arquitectura AWS | E23: Cloud | F23: BID | G23: Data | H23: =_xlfn.IFNA(VLOOKUP(F23,clientes!A:B,2,FALSE()),"--") -> Banco Interamericano de Desarrollo | I23: Inactivo | J23: Banco Interamericano de Desarrollo | K23: PURCHASE ORDER NO. 7000019059 | L23: Juan Bernal | M23: Marcela Sanchéz | N23: Moises Rojas | P23: Complete | Q23: N. A. | R23: 55130 - CLOUD 55131 - Ret | S23: No Aplica | U23: Contrato CJU - Sistema integrado de Secretaría Técnica - Fixed
A24: P1919 | B24: P0302 | C24: =F24&" - "&D24&" - "&E24 -> BID - Migración y Diseño de Arquitectura AWS - Ret | D24: Migración y Diseño de Arquitectura AWS | E24: Ret | F24: BID | G24: Operación | H24: =_xlfn.IFNA(VLOOKUP(F24,clientes!A:B,2,FALSE()),"--") -> Banco Interamericano de Desarrollo | I24: Inactivo | J24: Banco Interamericano de Desarrollo | K24: PURCHASE ORDER NO. 7000019059 | L24: Juan Bernal | M24: Marcela Sanchéz | N24: Carlos Sierra | O24: Whitman Rojas | P24: Complete | Q24: N. A. | R24: 55130 - CLOUD 55131 - Ret | S24: Whitman Rojas | U24: Contrato CJU - Sistema integrado de Secretaría Técnica - Ret SW
A25: P1933 | B25: P0280 | C25: =F25&" - "&D25&" - "&E25 -> DIA - Back Ups - Fixed | D25: Back Ups | E25: Fixed | F25: DIA | G25: Implementación | H25: =_xlfn.IFNA(VLOOKUP(F25,clientes!A:B,2,FALSE()),"--") -> DIAN | I25: Activo | J25: Dian | K25: Propuesta Backups | L25: Juan Bernal | M25: Ciliana Capera | N25: Nicolas Revollo | O25: Juan Sanchéz | P25: In Progress | Q25: N. A. | R25: 55145 | S25: Cloud Operations
A26: P1921 | B26: P0260 | C26: =F26&" - "&D26&" - "&E26 -> CAT - Nube Pública para Datalake - Ret | D26: Nube Pública para Datalake | E26: Ret | F26: CAT | G26: Operación | H26: =_xlfn.IFNA(VLOOKUP(F26,clientes!A:B,2,FALSE()),"--") -> Unidad Administrativa Especial de Catastro Distrital | I26: Inactivo | J26: Unidad Administrativa de Catastro | K26: OC 113430 | L26: Oscar Barragan | M26: Alejandra Gomez | N26: Carlos Sierra | O26: Marcelo Bonivento | P26: Complete | Q26: N. A. | R26: 55133 - Ret 55134 - CLOUD | S26: Cloud Operations | U26: Contrato FDN - Servicios profesionales Arquitectura - Fixed
A27: P1922 | B27: P0260 | C27: =F27&" - "&D27&" - "&E27 -> CAT - Nube Pública para Datalake - Cloud | D27: Nube Pública para Datalake | E27: Cloud | F27: CAT | G27: Data | H27: =_xlfn.IFNA(VLOOKUP(F27,clientes!A:B,2,FALSE()),"--") -> Unidad Administrativa Especial de Catastro Distrital | I27: Inactivo | J27: Unidad Administrativa de Catastro | K27: OC 113430 | L27: Oscar Barragan | M27: Alejandra Gomez | N27: Carlos Sierra | O27: Marcelo Bonivento | P27: Complete | Q27: N. A. | R27: 55133 - Ret 55134 - CLOUD | S27: Cloud Operations | U27: #VALUE!
A28: P1923 | B28: P0281 | C28: =F28&" - "&D28&" - "&E28 -> CCC - IaaS para DRP - Cloud | D28: IaaS para DRP | E28: Cloud | F28: CCC | G28: Data | H28: =_xlfn.IFNA(VLOOKUP(F28,clientes!A:B,2,FALSE()),"--") -> Cámara de Comercio de Cali | I28: Activo | J28: Cámara de Comercio de Cali | K28: Contrato OSJ 2023-0374 | L28: Kelly Carbonell | M28: Karen Arandia | N28: Nicolas Revollo | O28: Juan Sanchéz | P28: In Progress | Q28: N. A. | R28: 55135 | S28: Cloud Operations
A29: P1924 | B29: P0272 | C29: =F29&" - "&D29&" - "&E29 -> CSJ - Migración AWS - Fixed | D29: Migración AWS | E29: Fixed | F29: CSJ | G29: Implementación | H29: =_xlfn.IFNA(VLOOKUP(F29,clientes!A:B,2,FALSE()),"--") -> Consejo Superior de la Judicatura | I29: Inactivo | J29: Consejo Superior de la Judicatura | K29: OC 122576 | L29: David Cortes | M29: Andres Barrantes | N29: Nicolas Revollo | O29: Juan Sanchéz | P29: Complete | Q29: N. A. | R29: 55136 - Fixed 57148 - CLOUD | S29: Cloud Operations | U29: #VALUE!
A30: P1991 | B30: P0291 | C30: =F30&" - "&D30&" - "&E30 -> UNA - Unisalud - Ret | D30: Unisalud | E30: Ret | F30: UNA | G30: Operación | H30: =_xlfn.IFNA(VLOOKUP(F30,clientes!A:B,2,FALSE()),"--") -> Universidad Nacional de Colombia | I30: Activo | J30: Universidad Nacional | K30: NUVU - Proyectos - Documentos - 00. Administrativos - Todos los documentos | L30: Oscar Barragan | M30: Alejandra Gomez | N30: Nicolas Revollo | O30: Juan Sanchéz | P30: In Progress | Q30: N. A. | R30: 55203 | S30: No Aplica
A31: P1929 | B31: P0311 | C31: =F31&" - "&D31&" - "&E31 -> CJU - Sistema integrado de Secretaría Técnica - Ret | D31: Sistema integrado de Secretaría Técnica | E31: Ret | F31: CJU | G31: Operación | H31: =_xlfn.IFNA(VLOOKUP(F31,clientes!A:B,2,FALSE()),"--") -> Coljuegos | I31: Inactivo | J31: Coljuegos S.A | K31: CTO 323 - 2024 | L31: Juan Bernal | M31: Karen Arandia | N31: Moises Rojas | O31: Brandon Ardila | P31: Complete | Q31: N. A. | R31: 55140 - Fixed 55141 - Ret 55142 - Ret SW 55143 - CLOUD | S31: Brandon Ardila | U31: #N/A
A32: P1994 | B32: P0294 | C32: =F32&" - "&D32&" - "&E32 -> UNA - Regalías Sikie - Cloud | D32: Regalías Sikie | E32: Cloud | F32: UNA | G32: Data | H32: =_xlfn.IFNA(VLOOKUP(F32,clientes!A:B,2,FALSE()),"--") -> Universidad Nacional de Colombia | I32: Activo | J32: Universidad Nacional | K32: NUVU - Proyectos - Documentos - 00. Administrativos - Todos los documentos | L32: Oscar Barragan | M32: Alejandra Gomez | N32: Nicolas Revollo | O32: Juan Sanchéz | P32: In Progress | Q32: N. A. | R32: 55206 | S32: No Aplica
A33: P2537 | B33: P0294 | C33: =F33&" - "&D33&" - "&E33 -> UNA - Regalías Sikie - Ret | D33: Regalías Sikie | E33: Ret | F33: UNA | G33: Operación | H33: =_xlfn.IFNA(VLOOKUP(F33,clientes!A:B,2,FALSE()),"--") -> Universidad Nacional de Colombia | I33: Activo | J33: Universida Nacional | K33: NUVU - Proyectos - Documentos - 00. Administrativos - Todos los documentos | L33: Oscar Barragan | M33: Alejandra Gomez | N33: Nicolas Revollo | O33: Juan Sanchéz | P33: In Progress | R33: 2600 | S33: Christyan Gutiérrez
A34: P2537 | B34: P0294 | C34: UNA - Regalías Sikie - Ret | D34: Regalías Sikie | E34: Ret | F34: UNA | G34: Operación | H34: =_xlfn.IFNA(VLOOKUP(F34,clientes!A:B,2,FALSE()),"--") -> Universidad Nacional de Colombia | I34: Activo | L34: Oscar Barragan | M34: Alejandra Gómez | P34: In Progress
A35: P1977 | B35: P0298 | C35: =F35&" - "&D35&" - "&E35 -> UNA - Fortinet - Fixed | D35: Fortinet | E35: Fixed | F35: UNA | G35: Implementación | H35: =_xlfn.IFNA(VLOOKUP(F35,clientes!A:B,2,FALSE()),"--") -> Universidad Nacional de Colombia | I35: Activo | J35: Universidad Nacional | K35: NUVU - Proyectos - Documentos - 00. Administrativos - Todos los documentos | L35: Oscar Barragan | M35: Alejandra Gomez | N35: Nicolas Revollo | O35: Juan Sanchéz | P35: In Progress | Q35: N. A. | R35: 55190 - Fixed 55191 - CLOUD | S35: Cloud Operations
A36: P1934 | B36: P0308 | C36: =F36&" - "&D36&" - "&E36 -> EAF - Portal Colombia Aprende - Fixed | D36: Portal Colombia Aprende | E36: Fixed | F36: EAF | G36: Implementación | H36: =_xlfn.IFNA(VLOOKUP(F36,clientes!A:B,2,FALSE()),"--") -> Universidad EAFIT - Escuela de Administración, Finanzas e Instituto Tecnológico | I36: Inactivo | J36: Universidad EAFIT | K36: CONTRATO HIGH TECH SOFTWARE VF Final | L36: Kelly Carbonell | M36: Karen Arandia | N36: Moises Rojas | O36: Brandon Ardila | P36: Complete | Q36: N. A. | R36: 55146 - Fixed 55147 - Ret SW 55148 - CLOUD | S36: Operations_Team_01 | U36: Contrato UNA - Gestión de Información - Cloud
A37: P1935 | B37: P0308 | C37: =F37&" - "&D37&" - "&E37 -> EAF - Portal Colombia Aprende - Ret SW | D37: Portal Colombia Aprende | E37: Ret SW | F37: EAF | G37: Software SW | H37: =_xlfn.IFNA(VLOOKUP(F37,clientes!A:B,2,FALSE()),"--") -> Universidad EAFIT - Escuela de Administración, Finanzas e Instituto Tecnológico | I37: Inactivo | J37: Universidad EAFIT | K37: CONTRATO HIGH TECH SOFTWARE VF Final | L37: Kelly Carbonell | M37: Karen Arandia | N37: Moises Rojas | O37: Brandon Ardila | P37: Complete | Q37: N. A. | R37: 55146 - Fixed 55147 - Ret SW 55148 - CLOUD | S37: No Aplica | U37: Contrato UNA - Facultad de ingenieria - Ret
A38: P1936 | B38: P0308 | C38: =F38&" - "&D38&" - "&E38 -> EAF - Portal Colombia Aprende - Cloud | D38: Portal Colombia Aprende | E38: Cloud | F38: EAF | G38: Data | H38: =_xlfn.IFNA(VLOOKUP(F38,clientes!A:B,2,FALSE()),"--") -> Universidad EAFIT - Escuela de Administración, Finanzas e Instituto Tecnológico | I38: Inactivo | J38: Universidad EAFIT | K38: CONTRATO HIGH TECH SOFTWARE VF Final | L38: Kelly Carbonell | M38: Karen Arandia | N38: Moises Rojas | O38: Brandon Ardila | P38: Complete | Q38: N. A. | R38: 55146 - Fixed 55147 - Ret SW 55148 - CLOUD | S38: No Aplica | U38: Contrato UNA - Facultad de ingenieria - Cloud
A39: P1978 | B39: P0298 | C39: =F39&" - "&D39&" - "&E39 -> UNA - Fortinet - Cloud | D39: Fortinet | E39: Cloud | F39: UNA | G39: Data | H39: =_xlfn.IFNA(VLOOKUP(F39,clientes!A:B,2,FALSE()),"--") -> Universidad Nacional de Colombia | I39: Activo | J39: Universidad Nacional | K39: NUVU - Proyectos - Documentos - 00. Administrativos - Todos los documentos | L39: Oscar Barragan | M39: Alejandra Gomez | N39: Nicolas Revollo | O39: Juan Sanchéz | P39: In Progress | Q39: N. A. | R39: 55190 - Fixed 55191 - CLOUD | S39: No Aplica
A40: P1938 | B40: P0317 | C40: =F40&" - "&D40&" - "&E40 -> FDN - Tableros BI - Fixed | D40: Tableros BI | E40: Fixed | F40: FDN | G40: Implementación | H40: =_xlfn.IFNA(VLOOKUP(F40,clientes!A:B,2,FALSE()),"--") -> Financiera de Desarrollo Nacional | I40: Inactivo | J40: FND | K40: Contrato 71 de 2024 | L40: Juan Bernal | M40: Alejandra Gomez | N40: Nicolas Revollo | O40: Juan Sanchéz | P40: Complete | Q40: N. A. | R40: 55155 | S40: Operations_Team_01 | U40: Contrato BID - Development as a Service - Ret
A41: P1939 | B41: P0290 | C41: =F41&" - "&D41&" - "&E41 -> FOA - Gestión Integral Mojana - Fixed | D41: Gestión Integral Mojana | E41: Fixed | F41: FOA | G41: Implementación | H41: =_xlfn.IFNA(VLOOKUP(F41,clientes!A:B,2,FALSE()),"--") -> Fondo Adaptación | I41: Inactivo | J41: Fondo Adaptación | K41: OC 126506 | L41: Juan Bernal | M41: Karen Arandia | N41: Carlos Sierra | O41: Diego Saavedra | P41: Complete | Q41: N. A. | R41: 55151 - Fixed 55152 - Ret SW 55153 - CLOUD | S41: Diego Saavedra | U41: Contrato BID - Development as a Service - Cloud
A42: P1940 | B42: P0290 | C42: =F42&" - "&D42&" - "&E42 -> FOA - Gestión Integral Mojana - Ret SW | D42: Gestión Integral Mojana | E42: Ret SW | F42: FOA | G42: Software SW | H42: =_xlfn.IFNA(VLOOKUP(F42,clientes!A:B,2,FALSE()),"--") -> Fondo Adaptación | I42: Inactivo | J42: Fondo Adaptación | K42: OC 126506 | L42: Juan Bernal | M42: Karen Arandia | N42: Carlos Sierra | O42: Diego Saavedra | P42: Complete | Q42: N. A. | R42: 55151 - Fixed 55152 - Ret SW 55153 - CLOUD | S42: No Aplica | U42: Contrato BID - Development as a Service - Ret SW
A43: P1941 | B43: P0290 | C43: =F43&" - "&D43&" - "&E43 -> FOA - Gestión Integral Mojana - Cloud | D43: Gestión Integral Mojana | E43: Cloud | F43: FOA | G43: Data | H43: =_xlfn.IFNA(VLOOKUP(F43,clientes!A:B,2,FALSE()),"--") -> Fondo Adaptación | I43: Inactivo | J43: Fondo Adaptación | K43: OC 126506 | L43: Juan Bernal | M43: Karen Arandia | N43: Carlos Sierra | O43: Diego Saavedra | P43: Complete | Q43: N. A. | R43: 55151 - Fixed 55152 - Ret SW 55153 - CLOUD | S43: No Aplica | U43: Contrato FDN - Servicios de arquitectura - Cloud
A44: P1942 | B44: P0075 | C44: =F44&" - "&D44&" - "&E44 -> GLO - SmartCash - Operación - Cloud | D44: SmartCash - Operación | E44: Cloud | F44: GLO | G44: Data | H44: =_xlfn.IFNA(VLOOKUP(F44,clientes!A:B,2,FALSE()),"--") -> Global Securities | I44: Inactivo | J44: Global Securities S.A | K44: Cto CP Suite | L44: Kelly Carbonell | M44: Alejandra Gomez | N44: Carlos Sierra | O44: Angel Villasmil | P44: Complete | Q44: Miguel.Carrillo | R44: 55154 | S44: No Aplica | U44: Contrato UNA - Soporte y Mtto Quipu 2025 - Ret
A45: P1943 | B45: P0346 | C45: =F45&" - "&D45&" - "&E45 -> ICF - Evolución Datalake Fase1 2025 - Fixed | D45: Evolución Datalake Fase1 2025 | E45: Fixed | F45: ICF | G45: Implementación | H45: =_xlfn.IFNA(VLOOKUP(F45,clientes!A:B,2,FALSE()),"--") -> Instituto Colombiano Para La Evaluacion De La Educacion ICFES | I45: Inactivo | J45: Icfes | K45: OC 142744 | L45: Juan Bernal | M45: Ciliana Capera | N45: Moises Rojas | O45: Jairo Salas | P45: Complete | Q45: N. A. | R45: 55155 - Fixed 55156 - Ret 55157 - CLOUD 55158 - Ret SW | S45: Jairo Salas | U45: Contrato PON - IAPOL-G - IA Generative - Fixed
A46: P1944 | B46: P0346 | C46: =F46&" - "&D46&" - "&E46 -> ICF - Evolución Datalake Fase1 2025 - Ret | D46: Evolución Datalake Fase1 2025 | E46: Ret | F46: ICF | G46: Operación | H46: =_xlfn.IFNA(VLOOKUP(F46,clientes!A:B,2,FALSE()),"--") -> Instituto Colombiano Para La Evaluacion De La Educacion ICFES | I46: Inactivo | J46: Icfes | K46: OC 142744 | L46: Juan Bernal | M46: Ciliana Capera | N46: Moises Rojas | O46: Jairo Salas | P46: Complete | Q46: N. A. | R46: 55155 - Fixed 55156 - Ret 55157 - CLOUD 55158 - Ret SW | S46: Jairo Salas | U46: Contrato PON - IAPOL-G - IA Generative - Ret SW
A47: P1945 | B47: P0346 | C47: =F47&" - "&D47&" - "&E47 -> ICF - Evolución Datalake Fase1 2025 - Cloud | D47: Evolución Datalake Fase1 2025 | E47: Cloud | F47: ICF | G47: Data | H47: =_xlfn.IFNA(VLOOKUP(F47,clientes!A:B,2,FALSE()),"--") -> Instituto Colombiano Para La Evaluacion De La Educacion ICFES | I47: Inactivo | J47: Icfes | K47: OC 142744 | L47: Juan Bernal | M47: Ciliana Capera | N47: Moises Rojas | O47: Jairo Salas | P47: Complete | Q47: N. A. | R47: 55155 - Fixed 55156 - Ret 55157 - CLOUD 55158 - Ret SW | S47: No Aplica | U47: Contrato PON - IAPOL-G - IA Generative - Cloud
A48: P1946 | B48: P0346 | C48: =F48&" - "&D48&" - "&E48 -> ICF - Evolución Datalake Fase1 2025 - Ret SW | D48: Evolución Datalake Fase1 2025 | E48: Ret SW | F48: ICF | G48: Software SW | H48: =_xlfn.IFNA(VLOOKUP(F48,clientes!A:B,2,FALSE()),"--") -> Instituto Colombiano Para La Evaluacion De La Educacion ICFES | I48: Inactivo | J48: Icfes | K48: OC 142744 | L48: Juan Bernal | M48: Ciliana Capera | N48: Moises Rojas | O48: Jairo Salas | P48: Complete | Q48: N. A. | R48: 55155 - Fixed 55156 - Ret 55157 - CLOUD 55158 - Ret SW | S48: No Aplica | U48: Contrato PON - IAPOL-G - IA Generative - Ret
A49: P1983 | B49: P0300 | C49: =F49&" - "&D49&" - "&E49 -> UNA - Laboratorios Virtuales - Cloud | D49: Laboratorios Virtuales | E49: Cloud | F49: UNA | G49: Data | H49: =_xlfn.IFNA(VLOOKUP(F49,clientes!A:B,2,FALSE()),"--") -> Universidad Nacional de Colombia | I49: Activo | J49: Universidad Nacional | K49: OSE 90 4001 2024 SOL 20036 | L49: Oscar Barragan | M49: Alejandra Gomez | N49: Nicolas Revollo | O49: Juan Sanchéz | P49: Complete | Q49: N. A. | R49: 55195 | S49: Cloud Operations
A50: P1973 | B50: P0304 | C50: =F50&" - "&D50&" - "&E50 -> UNA - Editorial de UNAL - Cloud | D50: Editorial de UNAL | E50: Cloud | F50: UNA | G50: Data | H50: =_xlfn.IFNA(VLOOKUP(F50,clientes!A:B,2,FALSE()),"--") -> Universidad Nacional de Colombia | I50: Activo | J50: Universidad Nacional | K50: NUVU - Proyectos - 00. Administrativos - Todos los documentos | L50: Oscar Barragan | M50: Alejandra Gomez | N50: Nicolas Revollo | O50: Juan Sanchéz | P50: In Progress | Q50: N. A. | R50: 55185 | S50: No Aplica
A51: P1988 | B51: P0305 | C51: =F51&" - "&D51&" - "&E51 -> UNA - Repositorio - Cloud | D51: Repositorio | E51: Cloud | F51: UNA | G51: Data | H51: =_xlfn.IFNA(VLOOKUP(F51,clientes!A:B,2,FALSE()),"--") -> Universidad Nacional de Colombia | I51: Activo | J51: Universidad Nacional | K51: NUVU - Proyectos - Documentos - 00. Administrativos - Todos los documentos | L51: Oscar Barragan | M51: Alejandra Gomez | N51: Nicolas Revollo | O51: Juan Sanchéz | P51: In Progress | Q51: N. A. | R51: 55200 | S51: No Aplica
A52: P1982 | B52: P0306 | C52: =F52&" - "&D52&" - "&E52 -> UNA - HPC Registro y Matrícula - Cloud | D52: HPC Registro y Matrícula | E52: Cloud | F52: UNA | G52: Data | H52: =_xlfn.IFNA(VLOOKUP(F52,clientes!A:B,2,FALSE()),"--") -> Universidad Nacional de Colombia | I52: Activo | J52: Universidad Nacional | K52: NUVU - Proyectos - 00. Administrativo - Todos los documentos | L52: Oscar Barragan | M52: Alejandra Gomez | N52: Nicolas Revollo | O52: Juan Sanchéz | P52: In Progress | Q52: N. A. | R52: 55194 | S52: No Aplica
A53: P1951 | B53: P0316 | C53: =F53&" - "&D53&" - "&E53 -> MTC - Ciudades y territorios inteligentes Mintic - Ret | D53: Ciudades y territorios inteligentes Mintic | E53: Ret | F53: MTC | G53: Operación | H53: =_xlfn.IFNA(VLOOKUP(F53,clientes!A:B,2,FALSE()),"--") -> MinTic | I53: Inactivo | J53: Mintic | K53: NUVU - Proyectos - 01. Habilitacion - Todos los documentos | L53: Diana Rojas | M53: Karen Arandia | N53: Nicolas Revollo | O53: Juan Sanchéz | P53: Complete | Q53: N. A. | R53: 55163 - Ret 55164 - Fixed 55165 - CLOUD | S53: Operations_Team_01 | U53: Contrato FOA - Evolución Integral Mojana - Ret SW
A54: P1952 | B54: P0316 | C54: =F54&" - "&D54&" - "&E54 -> MTC - Ciudades y territorios inteligentes Mintic - Fixed | D54: Ciudades y territorios inteligentes Mintic | E54: Fixed | F54: MTC | G54: Implementación | H54: =_xlfn.IFNA(VLOOKUP(F54,clientes!A:B,2,FALSE()),"--") -> MinTic | I54: Inactivo | J54: Mintic | K54: NUVU - Proyectos - 01. Habilitacion - Todos los documentos | L54: Diana Rojas | M54: Karen Arandia | N54: Nicolas Revollo | O54: Juan Sanchéz | P54: Complete | Q54: N. A. | R54: 55163 - Ret 55164 - Fixed 55165 - CLOUD | S54: Cloud Operations | U54: Contrato FOA - Evolución Integral Mojana - Ret Other Vendors
A55: P1953 | B55: P0316 | C55: =F55&" - "&D55&" - "&E55 -> MTC - Ciudades y territorios inteligentes Mintic - Cloud | D55: Ciudades y territorios inteligentes Mintic | E55: Cloud | F55: MTC | G55: Data | H55: =_xlfn.IFNA(VLOOKUP(F55,clientes!A:B,2,FALSE()),"--") -> MinTic | I55: Inactivo | J55: Mintic | K55: NUVU - Proyectos - 01. Habilitacion - Todos los documentos | L55: Diana Rojas | M55: Karen Arandia | N55: Nicolas Revollo | O55: Juan Sanchéz | P55: Complete | Q55: N. A. | R55: 55163 - Ret 55164 - Fixed 55165 - CLOUD | S55: No Aplica | U55: Contrato UNA - Facultad de Derecho concurso méritos - Cloud
A56: P1954 | B56: P0309 | C56: =F56&" - "&D56&" - "&E56 -> MTC - Microcentros AI - Ret | D56: Microcentros AI | E56: Ret | F56: MTC | G56: Operación | H56: =_xlfn.IFNA(VLOOKUP(F56,clientes!A:B,2,FALSE()),"--") -> MinTic | I56: Inactivo | J56: Mintic | K56: NUVU - Proyectos - Documentos - 01. Documentación Esencial - Todos los documentos | L56: Diana Rojas | M56: Karen Arandia | N56: Carlos Sierra | O56: Jose Gallego | P56: Complete | Q56: N. A. | R56: 55166 - Ret 55167 - CLOUD | S56: Operations_Team_01 | U56: Contrato UNA - Facultad de Derecho concurso méritos - Ret
A57: P1955 | B57: P0309 | C57: =F57&" - "&D57&" - "&E57 -> MTC - Microcentros AI - Cloud | D57: Microcentros AI | E57: Cloud | F57: MTC | G57: Data | H57: =_xlfn.IFNA(VLOOKUP(F57,clientes!A:B,2,FALSE()),"--") -> MinTic | I57: Inactivo | J57: Mintic | K57: NUVU - Proyectos - Documentos - 01. Documentación Esencial - Todos los documentos | L57: Diana Rojas | M57: Karen Arandia | N57: Carlos Sierra | O57: Jose Gallego | P57: Complete | Q57: N. A. | R57: 55166 - Ret 55167 - CLOUD | S57: No Aplica | U57: Contrato UNA - OSE 26 Admisiones - Cloud
A58: P1959 | B58: P0301 | C58: =F58&" - "&D58&" - "&E58 -> SAN - Soporte y Mantenimiento Quipu 2024-25 - Ret | D58: Soporte y Mantenimiento Quipu 2024-25 | E58: Ret | F58: SAN | G58: Operación | H58: =_xlfn.IFNA(VLOOKUP(F58,clientes!A:B,2,FALSE()),"--") -> Sanidad | I58: Inactivo | J58: Dirección de Sanidad | K58: Contrato 07-7-20157-24 | L58: Juan Bernal | M58: Marcela Sanchéz | N58: Carlos Sierra | O58: Gersón Pineda | P58: Complete | Q58: David.Gomez | R58: 55171 | S58: Operations_Team_01 | U58: Contrato UNA - OSE 43 Moodle Extensión - Cloud
A59: P1960 | B59: P0307 | C59: =F59&" - "&D59&" - "&E59 -> SDH - Datalake Secretaria del Hábitat - Ret SW | D59: Datalake Secretaria del Hábitat | E59: Ret SW | F59: SDH | G59: Software SW | H59: =_xlfn.IFNA(VLOOKUP(F59,clientes!A:B,2,FALSE()),"--") -> Secretaria Distrital del Hábitat | I59: Inactivo | J59: Secretaria Distrital del Hábitat | K59: Contrato No 1558-2024 | L59: David Cortes | M59: Alejandra Gomez | N59: Moises Rojas | O59: Jairo Salas | P59: Complete | Q59: N. A. | R59: 55172 - Ret SW 55173 - CLOUD 55174 - Ret | S59: No Aplica | U59: Contrato UNA - OSE 43 Moodle Extensión - Ret
A60: P1961 | B60: P0307 | C60: =F60&" - "&D60&" - "&E60 -> SDH - Datalake Secretaria del Hábitat - Cloud | D60: Datalake Secretaria del Hábitat | E60: Cloud | F60: SDH | G60: Data | H60: =_xlfn.IFNA(VLOOKUP(F60,clientes!A:B,2,FALSE()),"--") -> Secretaria Distrital del Hábitat | I60: Inactivo | J60: Secretaria Distrital del Hábitat | K60: Contrato No 1558-2024 | L60: David Cortes | M60: Alejandra Gomez | N60: Moises Rojas | O60: Jairo Salas | P60: Complete | Q60: N. A. | R60: 55172 - Ret SW 55173 - CLOUD 55174 - Ret | S60: No Aplica | U60: Contrato UNA - Dinara de UNAL - Ret
A61: P1962 | B61: P0307 | C61: =F61&" - "&D61&" - "&E61 -> SDH - Datalake Secretaria del Hábitat - Ret | D61: Datalake Secretaria del Hábitat | E61: Ret | F61: SDH | G61: Operación | H61: =_xlfn.IFNA(VLOOKUP(F61,clientes!A:B,2,FALSE()),"--") -> Secretaria Distrital del Hábitat | I61: Inactivo | J61: Secretaria Distrital del Hábitat | K61: Contrato No 1558-2024 | L61: David Cortes | M61: Alejandra Gomez | N61: Moises Rojas | O61: Jairo Salas | P61: Complete | Q61: N. A. | R61: 55172 - Ret SW 55173 - CLOUD 55174 - Ret | S61: Operations_Team_01 | U61: Contrato UNA - Dinara de UNAL - Cloud
A62: P1963 | B62: P0332 | C62: =F62&" - "&D62&" - "&E62 -> SOC - IA Sociedades 2024-2025 - Cloud | D62: IA Sociedades 2024-2025 | E62: Cloud | F62: SOC | G62: Data | H62: =_xlfn.IFNA(VLOOKUP(F62,clientes!A:B,2,FALSE()),"--") -> Superintendencia de Sociedades | I62: Inactivo | J62: Supersociedades | K62: OC139384 00. Administrativo | L62: Daniel Sebastian Vargas | M62: Marcela Sanchéz | N62: Carlos Sierra | O62: Ariane Hernandez | P62: Complete | Q62: Miguel.Carrillo | R62: 55175 - CLOUD 55176 - Ret | S62: No Aplica | U62: Contrato UNA - Facultad de Derecho - Cloud
A63: P1964 | B63: P0332 | C63: =F63&" - "&D63&" - "&E63 -> SOC - IA Sociedades 2024-2025 - Ret | D63: IA Sociedades 2024-2025 | E63: Ret | F63: SOC | G63: Operación | H63: =_xlfn.IFNA(VLOOKUP(F63,clientes!A:B,2,FALSE()),"--") -> Superintendencia de Sociedades | I63: Inactivo | J63: Supersociedades | K63: OC139384 00. Administrativo | L63: Daniel Sebastian Vargas | M63: Marcela Sanchéz | N63: Carlos Sierra | O63: Ariane Hernandez | P63: Complete | Q63: Miguel.Carrillo | R63: 55175 - CLOUD 55176 - Ret | S63: Operations_Team_01 | U63: Contrato UNA - Facultad de Derecho - Ret
A64: P1928 | B64: P0311 | C64: =F64&" - "&D64&" - "&E64 -> CJU - Sistema integrado de Secretaría Técnica - Fixed | D64: Sistema integrado de Secretaría Técnica | E64: Fixed | F64: CJU | G64: Implementación | H64: =_xlfn.IFNA(VLOOKUP(F64,clientes!A:B,2,FALSE()),"--") -> Coljuegos | I64: Activo | J64: Coljuegos S.A | K64: CTO 323 - 2024 | L64: Juan Bernal | M64: Karen Arandia | N64: Moises Rojas | O64: Brandon Ardila | P64: In Progress | Q64: N. A. | R64: 55140 - Fixed 55141 - Ret 55142 - Ret SW 55143 - CLOUD | S64: Brandon Ardila
A65: P1930 | B65: P0311 | C65: =F65&" - "&D65&" - "&E65 -> CJU - Sistema integrado de Secretaría Técnica - Ret SW | D65: Sistema integrado de Secretaría Técnica | E65: Ret SW | F65: CJU | G65: Software SW | H65: =_xlfn.IFNA(VLOOKUP(F65,clientes!A:B,2,FALSE()),"--") -> Coljuegos | I65: Activo | J65: Coljuegos S.A | K65: CTO 323 - 2024 | L65: Juan Bernal | M65: Karen Arandia | N65: Moises Rojas | O65: Brandon Ardila | P65: In Progress | Q65: N. A. | R65: 55140 - Fixed 55141 - Ret 55142 - Ret SW 55143 - CLOUD | S65: No Aplica
A66: P1931 | B66: P0311 | C66: =F66&" - "&D66&" - "&E66 -> CJU - Sistema integrado de Secretaría Técnica - Cloud | D66: Sistema integrado de Secretaría Técnica | E66: Cloud | F66: CJU | G66: Data | H66: =_xlfn.IFNA(VLOOKUP(F66,clientes!A:B,2,FALSE()),"--") -> Coljuegos | I66: Activo | J66: Coljuegos S.A | K66: CTO 323 - 2024 | L66: Juan Bernal | M66: Karen Arandia | N66: Moises Rojas | O66: Brandon Ardila | P66: In Progress | Q66: N. A. | R66: 55140 - Fixed 55141 - Ret 55142 - Ret SW 55143 - CLOUD | S66: No Aplica
A67: P1937 | B67: P0318 | C67: =F67&" - "&D67&" - "&E67 -> FDN - Servicios profesionales Arquitectura - Fixed | D67: Servicios profesionales Arquitectura | E67: Fixed | F67: FDN | G67: Implementación | H67: =_xlfn.IFNA(VLOOKUP(F67,clientes!A:B,2,FALSE()),"--") -> Financiera de Desarrollo Nacional | I67: Activo | J67: FND | K67: Pedido 4402419 HIGH TECH SOFTWARE SAS | L67: David Cortes | M67: Alejandra Gomez | N67: Nicolas Revollo | O67: Juan Sanchéz | P67: In Progress | Q67: N. A. | R67: 55149 - Fixed | S67: Operations_Team_01
A68: P1969 | B68: P0322 | C68: =F68&" - "&D68&" - "&E68 -> UCA - ODS 1512 - Soporte y Mtto Quipu 24-25 - Ret | D68: ODS 1512 - Soporte y Mtto Quipu 24-25 | E68: Ret | F68: UCA | G68: Operación | H68: =_xlfn.IFNA(VLOOKUP(F68,clientes!A:B,2,FALSE()),"--") -> Universidad de Caldas | I68: Inactivo | J68: Universidad de Caldas | K68: ODS 1512-2024 | L68: Kelly Carbonell | M68: Alejandra Gomez | N68: Carlos Sierra | O68: Sebastian Vidal | P68: Complete | Q68: Valentina.Salazar | R68: 55181 | S68: Operations_Team_UCA | U68: Contrato CJU - Vigilancia y MET Plus - Ret SW
A69: P1949 | B69: P0320 | C69: =F69&" - "&D69&" - "&E69 -> MMN - Cloud Sistema de Recaudo - Fixed | D69: Cloud Sistema de Recaudo | E69: Fixed | F69: MMN | G69: Implementación | H69: =_xlfn.IFNA(VLOOKUP(F69,clientes!A:B,2,FALSE()),"--") -> Empresa De Transporte Masivo Del Valle De Aburrá Limitada | I69: Activo | J69: Metro de Medellín | K69: 01. Documentación esencial | L69: Diana Rojas | M69: Daniela Muñoz | N69: Nicolas Revollo | O69: Juan Sanchéz | P69: In Progress | Q69: N. A. | R69: 55161 - Fixed 55162 - CLOUD | S69: Cloud Operations
A70: P1950 | B70: P0320 | C70: =F70&" - "&D70&" - "&E70 -> MMN - Cloud Sistema de Recaudo - Cloud | D70: Cloud Sistema de Recaudo | E70: Cloud | F70: MMN | G70: Data | H70: =_xlfn.IFNA(VLOOKUP(F70,clientes!A:B,2,FALSE()),"--") -> Empresa De Transporte Masivo Del Valle De Aburrá Limitada | I70: Activo | J70: Metro de Medellín | K70: 01. Documentación esencial | L70: Diana Rojas | M70: Daniela Muñoz | N70: Nicolas Revollo | O70: Juan Sanchéz | P70: In Progress | Q70: N. A. | R70: 55161 - Fixed 55162 - CLOUD | S70: No Aplica
A71: P2225 | B71: P0320 | C71: =F71&" - "&D71&" - "&E71 -> MMN - Cloud Sistema de Recaudo - Ret Other Vendors | D71: Cloud Sistema de Recaudo | E71: Ret Other Vendors | F71: MMN | G71: Operación | H71: =_xlfn.IFNA(VLOOKUP(F71,clientes!A:B,2,FALSE()),"--") -> Empresa De Transporte Masivo Del Valle De Aburrá Limitada | I71: Activo | J71: Metro de Medellín | K71: 01. Documentación esencial | L71: Diana Rojas | M71: Daniela Muñoz | N71: Nicolas Revollo | O71: Juan Sanchéz | P71: In Progress | Q71: N. A. | R71: 67635 - Other Vendor | S71: No Aplica
A72: P2310 | B72: P0320 | C72: =F72&" - "&D72&" - "&E72 -> MMN - Cloud Sistema de Recaudo - Ret | D72: Cloud Sistema de Recaudo | E72: Ret | F72: MMN | G72: Operación | H72: =_xlfn.IFNA(VLOOKUP(F72,clientes!A:B,2,FALSE()),"--") -> Empresa De Transporte Masivo Del Valle De Aburrá Limitada | I72: Activo | J72: Metro de Medellín | K72: 01. Documentación esencial | L72: Diana Rojas | M72: Daniela Muñoz | N72: Nicolas Revollo | O72: Juan Sanchéz | P72: In Progress | Q72: N. A. | R72: 70411 - Ret | S72: No Aplica
A73: P1965 | B73: P0334 | C73: =F73&" - "&D73&" - "&E73 -> SPD - Repositorio Único de Datos - Fixed | D73: Repositorio Único de Datos | E73: Fixed | F73: SPD | G73: Implementación | H73: =_xlfn.IFNA(VLOOKUP(F73,clientes!A:B,2,FALSE()),"--") -> Superintendencia Servicios Públicos Domiciliarios | I73: Activo | J73: Superservicios | K73: PO-140333_v1_20241227 | L73: Miguel Garcia | M73: Ciliana Capera | N73: Moises Rojas | O73: Santiago Villegas | P73: In Progress | Q73: N. A. | R73: 55177 - Fixed 55178 - Ret SW 55179 - CLOUD | S73: Santiago Villegas
A74: P1966 | B74: P0334 | C74: =F74&" - "&D74&" - "&E74 -> SPD - Repositorio Único de Datos - Ret SW | D74: Repositorio Único de Datos | E74: Ret SW | F74: SPD | G74: Software SW | H74: Super servicios | I74: Activo | J74: Superservicios | K74: PO-140333_v1_20241227 | L74: Miguel Garcia | M74: Ciliana Capera | N74: Moises Rojas | O74: Santiago Villegas | P74: In Progress | Q74: N. A. | R74: 55177 - Fixed 55178 - Ret SW 55179 - CLOUD | S74: No Aplica
A75: P1967 | B75: P0334 | C75: =F75&" - "&D75&" - "&E75 -> SPD - Repositorio Único de Datos - Cloud | D75: Repositorio Único de Datos | E75: Cloud | F75: SPD | G75: Data | H75: Super servicios | I75: Activo | J75: Superservicios | K75: PO-140333_v1_20241227 | L75: Miguel Garcia | M75: Ciliana Capera | N75: Moises Rojas | O75: Santiago Villegas | P75: In Progress | Q75: N. A. | R75: 55177 - Fixed 55178 - Ret SW 55179 - CLOUD | S75: Santiago Villegas
A76: P1979 | B76: P0336 | C76: =F76&" - "&D76&" - "&E76 -> UNA - Gestión de Información - Fixed | D76: Gestión de Información | E76: Fixed | F76: UNA | G76: Implementación | H76: =_xlfn.IFNA(VLOOKUP(F76,clientes!A:B,2,FALSE()),"--") -> Universidad Nacional de Colombia | I76: Activo | J76: Universida Nacional | K76: NUVU - Proyectos - Documentos - 00. Administrativo - Todos los documentos | L76: Oscar Barragan | M76: Alejandra Gomez | N76: Nicolas Revollo | O76: Juan Sanchéz | P76: In Progress | Q76: N. A. | R76: 55191 - Fixed 55192 - Ret 55193 - CLOUD | S76: Cloud Operations
A77: P1980 | B77: P0336 | C77: =F77&" - "&D77&" - "&E77 -> UNA - Gestión de Información - Ret | D77: Gestión de Información | E77: Ret | F77: UNA | G77: Operación | H77: =_xlfn.IFNA(VLOOKUP(F77,clientes!A:B,2,FALSE()),"--") -> Universidad Nacional de Colombia | I77: Activo | J77: Universida Nacional | K77: NUVU - Proyectos - Documentos - 00. Administrativo - Todos los documentos | L77: Oscar Barragan | M77: Alejandra Gomez | N77: Nicolas Revollo | O77: Juan Sanchéz | P77: In Progress | Q77: N. A. | R77: 55191 - Fixed 55192 - Ret 55193 - CLOUD | S77: Cloud Operations
A78: P1981 | B78: P0336 | C78: =F78&" - "&D78&" - "&E78 -> UNA - Gestión de Información - Cloud | D78: Gestión de Información | E78: Cloud | F78: UNA | G78: Data | H78: =_xlfn.IFNA(VLOOKUP(F78,clientes!A:B,2,FALSE()),"--") -> Universidad Nacional de Colombia | I78: Activo | J78: Universida Nacional | K78: NUVU - Proyectos - Documentos - 00. Administrativo - Todos los documentos | L78: Oscar Barragan | M78: Alejandra Gomez | N78: Nicolas Revollo | O78: Juan Sanchéz | P78: In Progress | Q78: N. A. | R78: 55191 - Fixed 55192 - Ret 55193 - CLOUD | S78: No Aplica
A79: P1989 | B79: P0330 | C79: =F79&" - "&D79&" - "&E79 -> UNA - Servicios Quipu - Fixed | D79: Servicios Quipu | E79: Fixed | F79: UNA | G79: Implementación | H79: =_xlfn.IFNA(VLOOKUP(F79,clientes!A:B,2,FALSE()),"--") -> Universidad Nacional de Colombia | I79: Inactivo | J79: Universidad Nacional | K79: OEF 3 | L79: Oscar Barragan | M79: Alejandra Gomez | N79: Carlos Sierra | O79: Angel Villasmil | P79: Complete | Q79: N. A. | R79: 55201 | S79: Operations_Team_01 | U79: Contrato CAT - Agente Cognitivo e Infraestructura AWS - Ret
A80: P1975 | B80: P0340 | C80: =F80&" - "&D80&" - "&E80 -> UNA - Facultad de ingenieria - Ret | D80: Facultad de ingenieria | E80: Ret | F80: UNA | G80: Operación | H80: =_xlfn.IFNA(VLOOKUP(F80,clientes!A:B,2,FALSE()),"--") -> Universidad Nacional de Colombia | I80: Activo | J80: Universidad Nacional | K80: NUVU - Proyectos - Documentos - 00. Administrativos - Todos los documentos | L80: Oscar Barragan | M80: Alejandra Gomez | N80: Nicolas Revollo | O80: Juan Sanchéz | P80: In Progress | Q80: N. A. | S80: Cloud Operations
A81: P2036 | B81: P0340 | C81: =F81&" - "&D81&" - "&E81 -> UNA - Facultad de ingenieria - Cloud | D81: Facultad de ingenieria | E81: Cloud | F81: UNA | G81: Data | H81: =_xlfn.IFNA(VLOOKUP(F81,clientes!A:B,2,FALSE()),"--") -> Universidad Nacional de Colombia | I81: Activo | J81: Universidad Nacional | K81: NUVU - Proyectos - Documentos - 00. Administrativos - Todos los documentos | L81: Oscar Barragan | M81: Alejandra Gomez | N81: Nicolas Revollo | O81: Juan Sanchéz | P81: In Progress | Q81: N. A.
A82: P1914 | B82: P0341 | C82: =F82&" - "&D82&" - "&E82 -> BID - Development as a Service - Fixed | D82: Development as a Service | E82: Fixed | F82: BID | G82: Implementación | H82: =_xlfn.IFNA(VLOOKUP(F82,clientes!A:B,2,FALSE()),"--") -> Banco Interamericano de Desarrollo | I82: Activo | J82: Banco Interamericano de Desarrollo | K82: PO 7000020361 & PO 7000021280 | L82: Juan Bernal | M82: Marcela Sanchéz | N82: Carlos Sierra | O82: Whitman Rojas | P82: In Progress | Q82: N. A. | R82: 55126 - Fixed 55127 - Ret 55128 - CLOUD 55129 - Ret SW | S82: Whitman Rojas
A83: P1992 | B83: P0181 | C83: =F83&" - "&D83&" - "&E83 -> WIT - Witty Operación - Ret | D83: Witty Operación | E83: Ret | F83: WIT | G83: Operación | H83: =_xlfn.IFNA(VLOOKUP(F83,clientes!A:B,2,FALSE()),"--") -> Witty | I83: Inactivo | J83: Inversiones Kappi S.A.S | K83: Contrato operación Kappi | M83: Daniela Muñoz | N83: Carlos Sierra | O83: Angel Villasmil | P83: Complete | Q83: Carlos.Aroca | R83: 55204 | S83: Operations_Team_01 | U83: #N/A
A84: P1993 | B84: P0296 | C84: =F84&" - "&D84&" - "&E84 -> SIC - Soporte infraestructura - Ret | D84: Soporte infraestructura | E84: Ret | F84: SIC | G84: Operación | H84: =_xlfn.IFNA(VLOOKUP(F84,clientes!A:B,2,FALSE()),"--") -> Superintendencia de Industria y Comercio | I84: Inactivo | J84: SIC | K84: OC 128682 | L84: Juan Bernal | M84: Marcela Sanchéz | N84: Carlos Sierra | O84: Gustavo Galvis | P84: Complete | Q84: Carlos.Aroca | R84: 55205 | S84: No Aplica | U84: #N/A
A85: P1915 | B85: P0341 | C85: =F85&" - "&D85&" - "&E85 -> BID - Development as a Service - Ret | D85: Development as a Service | E85: Ret | F85: BID | G85: Operación | H85: =_xlfn.IFNA(VLOOKUP(F85,clientes!A:B,2,FALSE()),"--") -> Banco Interamericano de Desarrollo | I85: Activo | J85: Banco Interamericano de Desarrollo | K85: PO 7000020361 & PO 7000021280 | L85: Juan Bernal | M85: Marcela Sanchéz | N85: Carlos Sierra | O85: Whitman Rojas | P85: In Progress | Q85: N. A. | R85: 55126 - Fixed 55127 - Ret 55128 - CLOUD 55129 - Ret SW | S85: Whitman Rojas
A86: P1916 | B86: P0341 | C86: =F86&" - "&D86&" - "&E86 -> BID - Development as a Service - Cloud | D86: Development as a Service | E86: Cloud | F86: BID | G86: Data | H86: =_xlfn.IFNA(VLOOKUP(F86,clientes!A:B,2,FALSE()),"--") -> Banco Interamericano de Desarrollo | I86: Activo | J86: Banco Interamericano de Desarrollo | K86: PO 7000020361 & PO 7000021280 | L86: Juan Bernal | M86: Marcela Sanchéz | N86: Carlos Sierra | O86: Whitman Rojas | P86: In Progress | Q86: N. A. | R86: 55126 - Fixed 55127 - Ret 55128 - CLOUD 55129 - Ret SW | S86: No Aplica
A87: P1917 | B87: P0341 | C87: =F87&" - "&D87&" - "&E87 -> BID - Development as a Service - Ret SW | D87: Development as a Service | E87: Ret SW | F87: BID | G87: Software SW | H87: =_xlfn.IFNA(VLOOKUP(F87,clientes!A:B,2,FALSE()),"--") -> Banco Interamericano de Desarrollo | I87: Activo | J87: Banco Interamericano de Desarrollo | K87: PO 7000020361 & PO 7000021280 | L87: Juan Bernal | M87: Marcela Sanchéz | N87: Carlos Sierra | O87: Whitman Rojas | P87: In Progress | Q87: N. A. | R87: 55126 - Fixed 55127 - Ret 55128 - CLOUD 55129 - Ret SW | S87: No Aplica
A88: P2030 | B88: P0343 | C88: =F88&" - "&D88&" - "&E88 -> FDN - Servicios de arquitectura - Cloud | D88: Servicios de arquitectura | E88: Cloud | F88: FDN | G88: Data | H88: =_xlfn.IFNA(VLOOKUP(F88,clientes!A:B,2,FALSE()),"--") -> Financiera de Desarrollo Nacional | I88: Activo | J88: FND | K88: Pedido 4402476 | L88: David Cortes | M88: Alejandra Gomez | N88: Nicolas Revollo | O88: Juan Sanchéz | P88: In Progress | Q88: N. A. | R88: 57152 - CLOUD | S88: No Aplica
A89: P1990 | B89: P0344 | C89: =F89&" - "&D89&" - "&E89 -> UNA - Soporte y Mtto Quipu 2025 - Ret | D89: Soporte y Mtto Quipu 2025 | E89: Ret | F89: UNA | G89: Operación | H89: =_xlfn.IFNA(VLOOKUP(F89,clientes!A:B,2,FALSE()),"--") -> Universidad Nacional de Colombia | I89: Activo | J89: Universidad Nacional | K89: NUVU - Proyectos - 00 Administrativo - Todos los documentos | L89: Oscar Barragan | M89: Alejandra Gomez | N89: Carlos Sierra | O89: Angel Villasmil | P89: In Progress | Q89: David.Gomez | R89: 55202 | S89: Operations_Team_01
A90: P2017 | B90: P0354 | C90: =F90&" - "&D90&" - "&E90 -> ACA - Agente Cognitivo y Migración - Fixed | D90: Agente Cognitivo y Migración | E90: Fixed | F90: ACA | G90: Implementación | H90: =_xlfn.IFNA(VLOOKUP(F90,clientes!A:B,2,FALSE()),"--") -> Alcaldia de Cali | I90: Inactivo | J90: Alcadia de Cali | K90: Sin Contrato | L90: Kelly Carbonell | M90: Karen Arandia | N90: Nicolas Revollo | O90: Juan Sanchéz | P90: Complete | Q90: N. A. | R90: 57143 - Fixed 57144 - CLOUD | S90: Cloud Operations | U90: #N/A
A91: P2018 | B91: P0354 | C91: =F91&" - "&D91&" - "&E91 -> ACA - Agente Cognitivo y Migración - Cloud | D91: Agente Cognitivo y Migración | E91: Cloud | F91: ACA | G91: Data | H91: =_xlfn.IFNA(VLOOKUP(F91,clientes!A:B,2,FALSE()),"--") -> Alcaldia de Cali | I91: Inactivo | J91: Alcadia de Cali | K91: Sin Contrato | L91: Kelly Carbonell | M91: Karen Arandia | N91: Nicolas Revollo | O91: Juan Sanchéz | P91: Complete | Q91: N. A. | R91: 57143 - Fixed 57144 - CLOUD | S91: No Aplica | U91: Contrato PRO - SmartCash - Operación - Ret
A92: P2009 | B92: P0347 | C92: =F92&" - "&D92&" - "&E92 -> PON - IAPOL-G - IA Generative - Fixed | D92: IAPOL-G - IA Generative | E92: Fixed | F92: PON | G92: Implementación | H92: =_xlfn.IFNA(VLOOKUP(F92,clientes!A:B,2,FALSE()),"--") -> Policia Nacional | I92: Activo | J92: Policia Nacional | K92: OC-152418 5. Documentos contractuales | L92: Daniel Sebastian Vargas | M92: Marcela Sanchéz | N92: Moises Rojas | O92: Juan Goméz | P92: In Progress | Q92: Victor.Castellanos | R92: 56833 - Fixed 56834 - Ret SW 56835 - Cloud | S92: Juan Goméz
A93: P2010 | B93: P0347 | C93: =F93&" - "&D93&" - "&E93 -> PON - IAPOL-G - IA Generative - Ret SW | D93: IAPOL-G - IA Generative | E93: Ret SW | F93: PON | G93: Software SW | H93: =_xlfn.IFNA(VLOOKUP(F93,clientes!A:B,2,FALSE()),"--") -> Policia Nacional | I93: Activo | J93: Policia Nacional | K93: OC-152418 5. Documentos contractuales | L93: Daniel Sebastian Vargas | M93: Marcela Sanchéz | N93: Moises Rojas | O93: Juan Goméz | P93: In Progress | Q93: Victor.Castellanos | R93: 56833 - Fixed 56834 - Ret SW 56835 - Cloud | S93: No Aplica
A94: P2011 | B94: P0347 | C94: =F94&" - "&D94&" - "&E94 -> PON - IAPOL-G - IA Generative - Cloud | D94: IAPOL-G - IA Generative | E94: Cloud | F94: PON | G94: Data | H94: =_xlfn.IFNA(VLOOKUP(F94,clientes!A:B,2,FALSE()),"--") -> Policia Nacional | I94: Activo | J94: Policia Nacional | K94: OC-152418 5. Documentos contractuales | L94: Daniel Sebastian Vargas | M94: Marcela Sanchéz | N94: Moises Rojas | O94: Juan Goméz | P94: In Progress | Q94: Victor.Castellanos | R94: 56833 - Fixed 56834 - Ret SW 56835 - Cloud | S94: No Aplica
A95: P2023 | B95: P0347 | C95: =F95&" - "&D95&" - "&E95 -> PON - IAPOL-G - IA Generative - Ret | D95: IAPOL-G - IA Generative | E95: Ret | F95: PON | G95: Operación | H95: =_xlfn.IFNA(VLOOKUP(F95,clientes!A:B,2,FALSE()),"--") -> Policia Nacional | I95: Activo | J95: Policia Nacional | K95: OC-152418 5. Documentos contractuales | L95: Daniel Sebastian Vargas | M95: Marcela Sanchéz | N95: Moises Rojas | O95: Juan Goméz | P95: In Progress | Q95: Victor.Castellanos | R95: 56833 - Fixed 56834 - Ret SW 56835 - Cloud | S95: Victor.Castellanos
A96: P2226 | B96: P0347 | C96: =F96&" - "&D96&" - "&E96 -> PON - IAPOL-G - IA Generative - Other Vendors | D96: IAPOL-G - IA Generative | E96: Other Vendors | F96: PON | G96: Operación | H96: =_xlfn.IFNA(VLOOKUP(F96,clientes!A:B,2,FALSE()),"--") -> Policia Nacional | I96: Activo | J96: Policia Nacional | K96: OC-152418 5. Documentos contractuales | L96: Daniel Sebastian Vargas | M96: Marcela Sanchéz | N96: Moises Rojas | O96: Juan Goméz | P96: In Progress | Q96: Victor.Castellanos | R96: 56833 - Fixed 56834 - Ret SW 56835 - Cloud | S96: Victor.Castellanos
A97: P2024 | B97: P0348 | C97: =F97&" - "&D97&" - "&E97 -> CSJ - Digitalización archivo físico - Cloud | D97: Digitalización archivo físico | E97: Cloud | F97: CSJ | G97: Data | H97: =_xlfn.IFNA(VLOOKUP(F97,clientes!A:B,2,FALSE()),"--") -> Consejo Superior de la Judicatura | I97: Inactivo | J97: Consejo Superior de la Judicatura | K97: Pendiente el contrato | L97: David Cortes | M97: Ciliana Capera | N97: Moises Rojas | O97: Gersón Pineda | P97: Complete | Q97: N. A. | R97: 57146 - CLOUD 57147 - Fixed | S97: No Aplica | U97: #N/A
A98: P2025 | B98: P0348 | C98: =F98&" - "&D98&" - "&E98 -> CSJ - Digitalización archivo físico - Fixed | D98: Digitalización archivo físico | E98: Fixed | F98: CSJ | G98: Implementación | H98: =_xlfn.IFNA(VLOOKUP(F98,clientes!A:B,2,FALSE()),"--") -> Consejo Superior de la Judicatura | I98: Inactivo | J98: Consejo Superior de la Judicatura | K98: Pendiente el contrato | L98: David Cortes | M98: Ciliana Capera | N98: Moises Rojas | O98: Gersón Pineda | P98: Complete | Q98: N. A. | R98: 57146 - CLOUD 57147 - Fixed | S98: Gersón Pineda | U98: #N/A
A99: P2026 | B99: P0272 | C99: =F99&" - "&D99&" - "&E99 -> CSJ - Migración AWS - Cloud | D99: Migración AWS | E99: Cloud | F99: CSJ | G99: Data | H99: =_xlfn.IFNA(VLOOKUP(F99,clientes!A:B,2,FALSE()),"--") -> Consejo Superior de la Judicatura | I99: Inactivo | J99: Consejo Superior de la Judicatura | K99: OC 122576 | L99: David Cortes | M99: Andres Barrantes | N99: Moises Rojas | O99: Gerson Pineda | P99: Complete | Q99: N. A. | R99: 55136 - Fixed 57148 - CLOUD | S99: No Aplica | U99: #N/A
A100: P2026 | B100: P0312 | C100: =F100&" - "&D100&" - "&E100 -> BLD - All-Start Program LATAM - Internal | D100: All-Start Program LATAM | E100: Internal | F100: BLD | G100: Interno | H100: =_xlfn.IFNA(VLOOKUP(F100,clientes!A:B,2,FALSE()),"--") -> Blend360 | I100: Activo | J100: N.A. | K100: N.A. | L100: N.A. | M100: N.A. | N100: N.A. | O100: N.A. | P100: In Progress | Q100: N. A. | R100: 5045 | S100: No Aplica | U100: Contrato UNA- OSE 3 Secretaría General Fixed
...

Sheet PRY&PM
A1: Status | B1: (All)
A2: Type Project | B2: (All)
A4: Project Manager | B4: Count of Project Name Full
A5: Daniel Sebastian Vargas | B5: 16
A6: David Cortes | B6: 33
A7: Diana Castro | B7: 11
A8: Diana Rojas | B8: 19
A9: Fernando Ortega | B9: 1
A10: Indira Duarte | B10: 4
A11: Juan Bernal | B11: 62
A12: Kelly Carbonell | B12: 41
A13: Miguel Garcia | B13: 15
A14: N.A. | B14: 10
A15: Oscar Barragan | B15: 61
A16: (blank) | B16: 8

Sheet Reportes
A1: Status | B1: Activo
A2: Type Project | B2: Implementación
A4: ID Old | B4: Project Name Full | C4: Project Manager
A5: P0280 | B5: DIA - Back Ups - Fixed | C5: Juan Bernal
A6: P0298 | B6: UNA - Fortinet - Fixed | C6: Oscar Barragan
A7: P0318 | B7: FDN - Servicios profesionales Arquitectura - Fixed | C7: David Cortes
A8: P0320 | B8: MMN - Cloud Sistema de Recaudo - Fixed | C8: Diana Rojas
A9: P0336 | B9: UNA - Gestión de Información - Fixed | C9: Oscar Barragan
A10: P0341 | B10: BID - Development as a Service - Fixed | C10: Diana Castro
A11: P0347 | B11: PON - IAPOL-G - IA Generative - Fixed | C11: Daniel Sebastian Vargas
A12: P0349 | B12: FOA - Evolución Integral Mojana - Fixed | C12: Daniel Sebastian Vargas
A13: P0358 | B13: CJU - Vigilancia y MET Plus - Fixed | C13: Juan Bernal
A14: P0360 | B14: UNA - Ofc Gestion Ambiental - Fixed | C14: Oscar Barragan
A15: P0363 | B15: CAT - Agente Cognitivo e Infraestructura AWS - Fixed | C15: Oscar Barragan
... A38: P0405 | B38: CO - ICFES - Citación con Georreferenciación - Fixed | C38: Juan Bernal
